{
    "info": {
		"_postman_id"   : "8ddc52f1-51c2-4f7b-865f-ce8392d6e4b3",
		"name"          : "@hades - admin/tenant",
		"schema"        : "https://schema.getpostman.com/json/collection/v2.1.0/collection.json"
    },
    "item": [
        {
			"name": "GraphQL - adminCreateTenant",
			"request": {
				"method": "POST",
				"header": [],
				"body": {
					"mode": "graphql",
					"graphql": {
						"query": "mutation ($payload:AdminCreateTenantInput!)\n{\n\tadminCreateTenant (payload:$payload)\n\t{\n\t\tid\n\t\tname\n\t\tcode\n\t\tlogo\n\t\tisActive\n\t\tdata\n\t\tcreatedAt\n\t\tupdatedAt\n\t}\n}",
						"variables": "{\n\t\"payload\":\n\t{\n\t\t\"id\": \"6861ce3e-6eb2-4eb9-8ef3-44543f0adfe7\", \n\t\t\"name\": \"w\", \n\t\t\"code\": \"8ebto4v2a2e2w9ogh8io5fxdxwf41wy6zqkofqgo4x3dy9m4gh\", \n\t\t\"logo\": \"m\", \n\t\t\"isActive\": true, \n\t\t\"data\": { \"foo\" : \"bar\" }\n\t}\n}"
					}
				},
				"url": {
					"raw": "{{URL}}/graphql",
					"host": [
						"{{URL}}"
					],
					"path": [
						"graphql"
					]
				}
			},
			"response": []
        },
        {
			"name": "GraphQL - adminCreateTenants",
			"request": {
				"method": "POST",
				"header": [],
				"body": {
					"mode": "graphql",
					"graphql": {
						"query": "mutation ($payload:[AdminCreateTenantInput]!)\n{\n\tadminCreateTenants (payload:$payload)\n}",
						"variables": "{\n\t\"payload\":\n\t[\n\t\t{\n\t\t\t\"id\": \"efc668b4-187e-4ec0-bdbe-b89169f7dc7c\", \n\t\t\t\"name\": \"f\", \n\t\t\t\"code\": \"dn9e6mxzzezpubj3ccd5vvgcs20kw3fv6cg1iqkba6m8dj755u\", \n\t\t\t\"logo\": \"v\", \n\t\t\t\"isActive\": false, \n\t\t\t\"data\": { \"foo\" : \"bar\" }\n\t\t},\n\t\t{\n\t\t\t\"id\": \"45834085-973c-4bc4-8527-2d08d48cc983\", \n\t\t\t\"name\": \"k\", \n\t\t\t\"code\": \"jhmwdgbm8yslzylu33hr1x7w39l55tm67hyzispdvpkmp4l58z\", \n\t\t\t\"logo\": \"7\", \n\t\t\t\"isActive\": true, \n\t\t\t\"data\": { \"foo\" : \"bar\" }\n\t\t},\n\t\t{\n\t\t\t\"id\": \"1e1f3a2b-d406-478b-94e0-b71d6de71118\", \n\t\t\t\"name\": \"0\", \n\t\t\t\"code\": \"1zuvun5oic5zijxa1ufcn9qychas40yl48fei7dpd3yrpxxqdx\", \n\t\t\t\"logo\": \"9\", \n\t\t\t\"isActive\": false, \n\t\t\t\"data\": { \"foo\" : \"bar\" }\n\t\t},\n\t\t{\n\t\t\t\"id\": \"cbf615d8-a90a-4bf9-b13c-7cc7bebf8269\", \n\t\t\t\"name\": \"s\", \n\t\t\t\"code\": \"juw4kqniu9esa0x5xtomahq844dpkmf89fsydjwh0cncf6k19p\", \n\t\t\t\"logo\": \"a\", \n\t\t\t\"isActive\": false, \n\t\t\t\"data\": { \"foo\" : \"bar\" }\n\t\t},\n\t\t{\n\t\t\t\"id\": \"04a20746-a5e0-4f2a-902c-47dd979c8dce\", \n\t\t\t\"name\": \"p\", \n\t\t\t\"code\": \"6vaex2c7yp8nl98c6rmj8tmgnicc37oyim8oylgrsib9aw5yjl\", \n\t\t\t\"logo\": \"z\", \n\t\t\t\"isActive\": true, \n\t\t\t\"data\": { \"foo\" : \"bar\" }\n\t\t},\n\t\t{\n\t\t\t\"id\": \"72dd8201-6b5a-41f2-9b5e-c3f07a34d701\", \n\t\t\t\"name\": \"q\", \n\t\t\t\"code\": \"eghmaxdc2r6e10tdx6diwez4tavuieqcz781aavfaqs0s9urgc\", \n\t\t\t\"logo\": \"b\", \n\t\t\t\"isActive\": false, \n\t\t\t\"data\": { \"foo\" : \"bar\" }\n\t\t},\n\t\t{\n\t\t\t\"id\": \"08aa128f-39fd-4d1e-a936-a05799406af2\", \n\t\t\t\"name\": \"7\", \n\t\t\t\"code\": \"v494tgedmfeb4ez7j53z2jrzbyrh387ncnxkr6cuvyrp7j3czs\", \n\t\t\t\"logo\": \"t\", \n\t\t\t\"isActive\": false, \n\t\t\t\"data\": { \"foo\" : \"bar\" }\n\t\t},\n\t\t{\n\t\t\t\"id\": \"1f133276-8ba7-411d-96d2-775c57697786\", \n\t\t\t\"name\": \"7\", \n\t\t\t\"code\": \"i8jz93wn83ua1j0yc3c3ehlap5vixe223aie415zp6s0an6j4e\", \n\t\t\t\"logo\": \"f\", \n\t\t\t\"isActive\": true, \n\t\t\t\"data\": { \"foo\" : \"bar\" }\n\t\t},\n\t\t{\n\t\t\t\"id\": \"68bf099a-e52d-443e-8f99-2fae59edeebe\", \n\t\t\t\"name\": \"g\", \n\t\t\t\"code\": \"9qr83ohaxyvxajbg9rveustjvf04u3329k1vc6raft5c5d2rsb\", \n\t\t\t\"logo\": \"4\", \n\t\t\t\"isActive\": false, \n\t\t\t\"data\": { \"foo\" : \"bar\" }\n\t\t},\n\t\t{\n\t\t\t\"id\": \"516d3d2b-bd8a-431f-bea6-f348a996c82f\", \n\t\t\t\"name\": \"v\", \n\t\t\t\"code\": \"8roufy1fez4u0foxxnlk8nzfw2q1mz1hrzh1qr8ho4vo7fvjl0\", \n\t\t\t\"logo\": \"9\", \n\t\t\t\"isActive\": false, \n\t\t\t\"data\": { \"foo\" : \"bar\" }\n\t\t},\n\t\t{\n\t\t\t\"id\": \"fea2e832-e1e6-400b-83ca-9aed78fbdd70\", \n\t\t\t\"name\": \"3\", \n\t\t\t\"code\": \"ejj2mkfv6pyogyifk5qzpmaozhn8j8bwa8tb30me03nbuifet5\", \n\t\t\t\"logo\": \"y\", \n\t\t\t\"isActive\": true, \n\t\t\t\"data\": { \"foo\" : \"bar\" }\n\t\t},\n\t\t{\n\t\t\t\"id\": \"30c1c487-0c17-443f-b9e3-4aa6ee12d719\", \n\t\t\t\"name\": \"i\", \n\t\t\t\"code\": \"wf3tqx7dosfsd7r19nrh0hrqguis3j9bju4j3qsjpfskbfmbc4\", \n\t\t\t\"logo\": \"n\", \n\t\t\t\"isActive\": false, \n\t\t\t\"data\": { \"foo\" : \"bar\" }\n\t\t},\n\t\t{\n\t\t\t\"id\": \"5a36559f-5506-4b66-9106-08738eb52d00\", \n\t\t\t\"name\": \"p\", \n\t\t\t\"code\": \"y9jo15felqgc6a6o3ad6ojtvjdz0l0bjfd8gdd6sqwgd4a61gx\", \n\t\t\t\"logo\": \"l\", \n\t\t\t\"isActive\": false, \n\t\t\t\"data\": { \"foo\" : \"bar\" }\n\t\t},\n\t\t{\n\t\t\t\"id\": \"afb91ecd-ed8d-49cb-9fd5-41006a0a9e0d\", \n\t\t\t\"name\": \"w\", \n\t\t\t\"code\": \"8rn8fnp1cttuibymekuv3vrm8dlg792pgdkwed9mmivx5tvqwj\", \n\t\t\t\"logo\": \"2\", \n\t\t\t\"isActive\": true, \n\t\t\t\"data\": { \"foo\" : \"bar\" }\n\t\t},\n\t\t{\n\t\t\t\"id\": \"5de29582-bcc7-4b3f-a4e5-24d12015c274\", \n\t\t\t\"name\": \"h\", \n\t\t\t\"code\": \"8mzpdx8mhy1vuqa0t4fee2kh2wpx3rfkf70fhbzhzri5ixtmxm\", \n\t\t\t\"logo\": \"s\", \n\t\t\t\"isActive\": false, \n\t\t\t\"data\": { \"foo\" : \"bar\" }\n\t\t},\n\t\t{\n\t\t\t\"id\": \"d6a6530f-f8c2-4e00-9d0b-7e4d91890ea0\", \n\t\t\t\"name\": \"z\", \n\t\t\t\"code\": \"u7ncnjeg79wnj3ngfvax2u7bgt23yamheuasa0jmu9wtfyi567\", \n\t\t\t\"logo\": \"3\", \n\t\t\t\"isActive\": false, \n\t\t\t\"data\": { \"foo\" : \"bar\" }\n\t\t},\n\t\t{\n\t\t\t\"id\": \"2b3169a3-1be9-4b1c-915d-fe02e774de78\", \n\t\t\t\"name\": \"e\", \n\t\t\t\"code\": \"xrkzg4my9dvpt9ff4604jbel532100a661z33pmghnf3z0kh8m\", \n\t\t\t\"logo\": \"6\", \n\t\t\t\"isActive\": true, \n\t\t\t\"data\": { \"foo\" : \"bar\" }\n\t\t},\n\t\t{\n\t\t\t\"id\": \"150cbebe-978f-4ac0-8025-f3b7b3ba4934\", \n\t\t\t\"name\": \"j\", \n\t\t\t\"code\": \"ldougk24cdgerrkazddkwfa482tvl58lx9w7usoc4qcfapcov1\", \n\t\t\t\"logo\": \"7\", \n\t\t\t\"isActive\": true, \n\t\t\t\"data\": { \"foo\" : \"bar\" }\n\t\t},\n\t\t{\n\t\t\t\"id\": \"ae407bbc-3a35-47fb-a588-8c15d4e2235d\", \n\t\t\t\"name\": \"7\", \n\t\t\t\"code\": \"230vgbr2e2upus2gkg3hhtazwwoalqwiwpp8n083uzhb080k2b\", \n\t\t\t\"logo\": \"5\", \n\t\t\t\"isActive\": true, \n\t\t\t\"data\": { \"foo\" : \"bar\" }\n\t\t},\n\t\t{\n\t\t\t\"id\": \"458809f8-492c-4172-a71e-cc8e3fe85983\", \n\t\t\t\"name\": \"f\", \n\t\t\t\"code\": \"rp54mfkdc619vn3azewiriz7n8br7g238pgne57ddl212lcc62\", \n\t\t\t\"logo\": \"8\", \n\t\t\t\"isActive\": false, \n\t\t\t\"data\": { \"foo\" : \"bar\" }\n\t\t}\n\t]\n}"
					}
				},
				"url": {
					"raw": "{{URL}}/graphql",
					"host": [
						"{{URL}}"
					],
					"path": [
						"graphql"
					]
				}
			},
			"response": []
        },
        {
			"name": "GraphQL - adminPaginateTenants",
			"request": {
				"method": "POST",
				"header": [],
				"body": {
					"mode": "graphql",
					"graphql": {
						"query": "query ($query:[QueryStatementInput] $constraint:[QueryStatementInput])\n{\n\tadminPaginateTenants (query:$query constraint:$constraint)\n\t{\n\t\ttotal\n\t\tcount\n\t\trows\n\t}\n}",
						"variables": "{\n\t\"query\":\n\t[\n\t\t{\n\t\t\t\"command\": \"OFFSET\",\n\t\t\t\"value\": 0\n\t\t},\n\t\t{\n\t\t\t\"command\": \"LIMIT\",\n\t\t\t\"value\": 10\n\t\t}\n\t]\n}"
					}
				},
				"url": {
					"raw": "{{URL}}/graphql",
					"host": [
						"{{URL}}"
					],
					"path": [
						"graphql"
					]
				}
			},
			"response": []
        },
        {
			"name": "GraphQL - adminGetTenants",
			"request": {
				"method": "POST",
				"header": [],
				"body": {
					"mode": "graphql",
					"graphql": {
						"query": "query ($query:[QueryStatementInput])\n{\n\tadminGetTenants (query: $query)\n\t{\n\t\tid\n\t\tname\n\t\tcode\n\t\tlogo\n\t\tisActive\n\t\tdata\n\t\tcreatedAt\n\t\tupdatedAt\n\t}\n}",
						"variables": "{\n\t\"query\":\n\t[\n\t\t{\n\t\t\t\"command\": \"WHERE\",\n\t\t\t\"column\": \"id\",\n\t\t\t\"operator\": \"EQUALS\",\n\t\t\t\"value\": \"6861ce3e-6eb2-4eb9-8ef3-44543f0adfe7\"\n\t\t}\n\t]\n}"
					}
				},
				"url": {
					"raw": "{{URL}}/graphql",
					"host": [
						"{{URL}}"
					],
					"path": [
						"graphql"
					]
				}
			},
			"response": []
        },
        {
			"name": "GraphQL - adminFindTenant",
			"request": {
				"method": "POST",
				"header": [],
				"body": {
					"mode": "graphql",
					"graphql": {
						"query": "query ($query:[QueryStatementInput])\n{\n\tadminFindTenant (query: $query)\n\t{\n\t\tid\n\t\tname\n\t\tcode\n\t\tlogo\n\t\tisActive\n\t\tdata\n\t\tcreatedAt\n\t\tupdatedAt\n\t}\n}",
						"variables": "{\n\t\"query\":\n\t[\n\t\t{\n\t\t\t\"command\": \"WHERE\",\n\t\t\t\"column\": \"id\",\n\t\t\t\"operator\": \"EQUALS\",\n\t\t\t\"value\": \"6861ce3e-6eb2-4eb9-8ef3-44543f0adfe7\"\n\t\t}\n\t]\n}"
					}
				},
				"url": {
					"raw": "{{URL}}/graphql",
					"host": [
						"{{URL}}"
					],
					"path": [
						"graphql"
					]
				}
			},
			"response": []
        },
        {
			"name": "GraphQL - adminFindTenantById",
			"request": {
				"method": "POST",
				"header": [],
				"body": {
					"mode": "graphql",
					"graphql": {
						"query": "query ($id:ID)\n{\n\tadminFindTenantById (id:$id)\n\t{\n\t\tid\n\t\tname\n\t\tcode\n\t\tlogo\n\t\tisActive\n\t\tdata\n\t\tcreatedAt\n\t\tupdatedAt\n\t}\n}",
						"variables": "{\n\t\"id\": \"6861ce3e-6eb2-4eb9-8ef3-44543f0adfe7\"\n}"
					}
				},
				"url": {
					"raw": "{{URL}}/graphql",
					"host": [
						"{{URL}}"
					],
					"path": [
						"graphql"
					]
				}
			},
			"response": []
        },
        {
			"name": "GraphQL - adminUpdateTenant",
			"request": {
				"method": "POST",
				"header": [],
				"body": {
					"mode": "graphql",
					"graphql": {
						"query": "mutation ($payload:AdminUpdateTenantInput!)\n{\n\tadminUpdateTenant (payload:$payload)\n\t{\n\t\tid\n\t\tname\n\t\tcode\n\t\tlogo\n\t\tisActive\n\t\tdata\n\t\tcreatedAt\n\t\tupdatedAt\n\t}\n}",
						"variables": "{\n\t\"payload\":\n\t{\n\t\t\"id\": \"6861ce3e-6eb2-4eb9-8ef3-44543f0adfe7\", \n\t\t\"name\": \"m\", \n\t\t\"code\": \"rqy5odgp6wnew6g009ic3r4xvsyk7pwwo3rqmyaufzd2h4m13i\", \n\t\t\"logo\": \"4\", \n\t\t\"isActive\": false, \n\t\t\"data\": { \"foo\" : \"bar\" }\n\t}\n}"
					}
				},
				"url": {
					"raw": "{{URL}}/graphql",
					"host": [
						"{{URL}}"
					],
					"path": [
						"graphql"
					]
				}
			},
			"response": []
        },
        {
			"name": "GraphQL - adminDeleteTenantById",
			"request": {
				"method": "POST",
				"header": [],
				"body": {
					"mode": "graphql",
					"graphql": {
						"query": "mutation ($id:ID!)\n{\n\tadminDeleteTenantById (id:$id)\n\t{\n\t\tid\n\t\tname\n\t\tcode\n\t\tlogo\n\t\tisActive\n\t\tdata\n\t\tcreatedAt\n\t\tupdatedAt\n\t}\n}",
						"variables": "{\n\t\"id\": \"6861ce3e-6eb2-4eb9-8ef3-44543f0adfe7\"\n}"
					}
				},
				"url": {
					"raw": "{{URL}}/graphql",
					"host": [
						"{{URL}}"
					],
					"path": [
						"graphql"
					]
				}
			},
			"response": []
        },
        {
			"name": "GraphQL - adminDeleteTenants",
			"request": {
				"method": "POST",
				"header": [],
				"body": {
					"mode": "graphql",
					"graphql": {
						"query": "mutation ($query:[QueryStatementInput])\n{\n\tadminDeleteTenants (query: $query)\n\t{\n\t\tid\n\t\tname\n\t\tcode\n\t\tlogo\n\t\tisActive\n\t\tdata\n\t\tcreatedAt\n\t\tupdatedAt\n\t}\n}",
						"variables": "{\n\t\"query\":\n\t[\n\t\t{\n\t\t\t\"command\": \"WHERE\",\n\t\t\t\"column\": \"id\",\n\t\t\t\"operator\": \"CONTAINS\",\n\t\t\t\"value\": \"%%\"\n\t\t}\n\t]\n}"
					}
				},
				"url": {
					"raw": "{{URL}}/graphql",
					"host": [
						"{{URL}}"
					],
					"path": [
						"graphql"
					]
				}
			},
			"response": []
        },
        {
			"name": "REST - admin/tenant",
			"request": {
				"method": "POST",
				"header": [
					{
						"key"   : "Content-Type",
						"name"  : "Content-Type",
						"type"  : "text",
						"value" : "application/json"
					}
				],
				"body": {
					"mode"  : "raw",
					"raw"   : "{\n\t\"id\": \"6861ce3e-6eb2-4eb9-8ef3-44543f0adfe7\", \n\t\"name\": \"w\", \n\t\"code\": \"m2gs54gixwep1mgjt324ol6ps2inok3c2zt1ua1t1yvmp1wrh2\", \n\t\"logo\": \"8\", \n\t\"isActive\": false, \n\t\"data\": { \"foo\" : \"bar\" }\n}",
					"options": {
						"raw": {
							"language": "json"
						}
					}
				},
				"url": {
					"raw": "{{URL}}/admin/tenant",
					"host": [
						"{{URL}}"
					],
					"path": [
						"admin",
						"tenant"
					]
				}
			},
			"response": []
        },
        {
			"name": "REST - admin/tenants",
			"request": {
				"method": "POST",
				"header": [
					{
						"key"   : "Content-Type",
						"name"  : "Content-Type",
						"type"  : "text",
						"value" : "application/json"
					}
				],
				"body": {
					"mode"  : "raw",
					"raw"   : "[\n\t{\n\t\t\"id\": \"d45e0465-c7de-4a4e-8b44-add5f9b0f2ef\", \n\t\t\"name\": \"f\", \n\t\t\"code\": \"lz0yemzt3y2uaasx9hppg798tinzbcz32vhniai2vydi3rt22k\", \n\t\t\"logo\": \"3\", \n\t\t\"isActive\": false, \n\t\t\"data\": { \"foo\" : \"bar\" }\n\t}, \n\t{\n\t\t\"id\": \"a98b5f52-92ed-4bd3-9ada-dc2ec6f12b19\", \n\t\t\"name\": \"z\", \n\t\t\"code\": \"po8huigsgn4firw78lcp3vsf7tqdyvrb1esqetz5h6koiqp609\", \n\t\t\"logo\": \"e\", \n\t\t\"isActive\": true, \n\t\t\"data\": { \"foo\" : \"bar\" }\n\t}, \n\t{\n\t\t\"id\": \"a51cb68d-bbfd-4577-b001-95904bd3b1ae\", \n\t\t\"name\": \"w\", \n\t\t\"code\": \"ca1t81shx9z2emiuld8s2o8arkhqfvzctwio2z6k6iozz2eblj\", \n\t\t\"logo\": \"2\", \n\t\t\"isActive\": false, \n\t\t\"data\": { \"foo\" : \"bar\" }\n\t}, \n\t{\n\t\t\"id\": \"7911e604-1337-4cf9-906d-755c4e45a0a6\", \n\t\t\"name\": \"h\", \n\t\t\"code\": \"8isopsn1y32ijc4wtdbav7eed77nhdvwfbl8j5at7csqxnlw61\", \n\t\t\"logo\": \"6\", \n\t\t\"isActive\": false, \n\t\t\"data\": { \"foo\" : \"bar\" }\n\t}, \n\t{\n\t\t\"id\": \"8c255ef6-cd73-4ae9-b863-460adbaef70f\", \n\t\t\"name\": \"m\", \n\t\t\"code\": \"flwnvol378pl2h6cvj79sti8qjgwrk1n3ns8b5v33r41u46gk7\", \n\t\t\"logo\": \"3\", \n\t\t\"isActive\": true, \n\t\t\"data\": { \"foo\" : \"bar\" }\n\t}, \n\t{\n\t\t\"id\": \"06cd3756-2198-45d7-b989-62df6c24767d\", \n\t\t\"name\": \"t\", \n\t\t\"code\": \"dk6dy975pjdh0yx00olfgm5vf5jeyrdg0j2dg9lp7e9sydv65y\", \n\t\t\"logo\": \"l\", \n\t\t\"isActive\": false, \n\t\t\"data\": { \"foo\" : \"bar\" }\n\t}, \n\t{\n\t\t\"id\": \"2857d2ed-ea5a-4b3f-a4b5-acb310359f1c\", \n\t\t\"name\": \"0\", \n\t\t\"code\": \"ddfw6bcvkgpkq59h488sl1ajqcchtxc574n6i70iu5nw1t1g25\", \n\t\t\"logo\": \"3\", \n\t\t\"isActive\": true, \n\t\t\"data\": { \"foo\" : \"bar\" }\n\t}, \n\t{\n\t\t\"id\": \"54f367a4-f0a0-4816-8163-98189be1fec7\", \n\t\t\"name\": \"9\", \n\t\t\"code\": \"aapfqiegxibabkbm12vkhvr5isa7is0ydw2l3lgrnyxfowzha6\", \n\t\t\"logo\": \"7\", \n\t\t\"isActive\": false, \n\t\t\"data\": { \"foo\" : \"bar\" }\n\t}, \n\t{\n\t\t\"id\": \"9b5bb2f2-9cfd-4e54-a2ba-5849c1ada154\", \n\t\t\"name\": \"c\", \n\t\t\"code\": \"x287i3ityl5denvg4gesifbwo3c49xi74cy0jlvna2b8pe4tch\", \n\t\t\"logo\": \"t\", \n\t\t\"isActive\": false, \n\t\t\"data\": { \"foo\" : \"bar\" }\n\t}, \n\t{\n\t\t\"id\": \"9ee6fe0f-5242-4445-9d69-dcfb06f8037d\", \n\t\t\"name\": \"i\", \n\t\t\"code\": \"3dmiidioayu98thf68e5gcjvsq57q0ie7k49u9fme664fq44qm\", \n\t\t\"logo\": \"d\", \n\t\t\"isActive\": true, \n\t\t\"data\": { \"foo\" : \"bar\" }\n\t}, \n\t{\n\t\t\"id\": \"b87d583b-1272-4841-999d-399d26c3f0fa\", \n\t\t\"name\": \"c\", \n\t\t\"code\": \"nqazyuqm7ijl461lvy4np6f4cfm91pn39bj00mse80agvfex8i\", \n\t\t\"logo\": \"h\", \n\t\t\"isActive\": false, \n\t\t\"data\": { \"foo\" : \"bar\" }\n\t}, \n\t{\n\t\t\"id\": \"9803e5c2-1834-4077-be3c-7c7150b538d2\", \n\t\t\"name\": \"y\", \n\t\t\"code\": \"ghtkkgyiaabcpsgem8gwdzkgs9l9gk6se08fvmifvyhqgj917w\", \n\t\t\"logo\": \"2\", \n\t\t\"isActive\": true, \n\t\t\"data\": { \"foo\" : \"bar\" }\n\t}, \n\t{\n\t\t\"id\": \"f8661e6c-159a-46f6-97e1-e90cb166bab0\", \n\t\t\"name\": \"o\", \n\t\t\"code\": \"p7t5felwaxaca9y09u4mtmk7dto4amw5dxv4xipqxn7hliiuma\", \n\t\t\"logo\": \"u\", \n\t\t\"isActive\": false, \n\t\t\"data\": { \"foo\" : \"bar\" }\n\t}, \n\t{\n\t\t\"id\": \"59ae6090-9539-4eb2-ba55-e8edd0be4b13\", \n\t\t\"name\": \"6\", \n\t\t\"code\": \"u2a9u9m703tf2bo8cu5i6mjyoy3fs4zteod9aejt5azrls9p91\", \n\t\t\"logo\": \"0\", \n\t\t\"isActive\": false, \n\t\t\"data\": { \"foo\" : \"bar\" }\n\t}, \n\t{\n\t\t\"id\": \"a05e0338-aa65-48ab-ab93-b035d16d7cc0\", \n\t\t\"name\": \"f\", \n\t\t\"code\": \"qlhk7efs7orv3q31z7upshf96pqgvzp3ts2x5jwzsjd74ky4jr\", \n\t\t\"logo\": \"s\", \n\t\t\"isActive\": true, \n\t\t\"data\": { \"foo\" : \"bar\" }\n\t}, \n\t{\n\t\t\"id\": \"c37bf91f-b127-4d09-a68f-eadf06e2874b\", \n\t\t\"name\": \"8\", \n\t\t\"code\": \"dkqdh5o0yrd0zs2rrzse30oh1xzmnda4c4xzl7qqmu51jfokm3\", \n\t\t\"logo\": \"i\", \n\t\t\"isActive\": false, \n\t\t\"data\": { \"foo\" : \"bar\" }\n\t}, \n\t{\n\t\t\"id\": \"e1d524bc-5153-4b61-a2ce-5c029d6ffc15\", \n\t\t\"name\": \"f\", \n\t\t\"code\": \"ew8cecschtbblz5ifg9njmb0mcoirsgfpfgvbr5ldzhgvbvzyz\", \n\t\t\"logo\": \"s\", \n\t\t\"isActive\": false, \n\t\t\"data\": { \"foo\" : \"bar\" }\n\t}, \n\t{\n\t\t\"id\": \"6640e64e-f2e5-4e69-926a-20d6f9d8be30\", \n\t\t\"name\": \"t\", \n\t\t\"code\": \"6eep5f4orxnfgl8e65n9fq7fr99nroc3ybcvvmug0jwa2wvlln\", \n\t\t\"logo\": \"4\", \n\t\t\"isActive\": true, \n\t\t\"data\": { \"foo\" : \"bar\" }\n\t}, \n\t{\n\t\t\"id\": \"d1cd065f-60aa-423d-93f8-dc96c9ca9d4d\", \n\t\t\"name\": \"o\", \n\t\t\"code\": \"y6ov224kqjof1zbzpxnnz5atsunt4x84p2eudkvwz0uwdp53yi\", \n\t\t\"logo\": \"f\", \n\t\t\"isActive\": true, \n\t\t\"data\": { \"foo\" : \"bar\" }\n\t}, \n\t{\n\t\t\"id\": \"75b7f478-a7ef-44d5-be3b-7f40d4ee3880\", \n\t\t\"name\": \"q\", \n\t\t\"code\": \"dtb9ohk25cce7yj4xjactxeyw4ngvyvcm1sbald16b8tnf2e11\", \n\t\t\"logo\": \"q\", \n\t\t\"isActive\": false, \n\t\t\"data\": { \"foo\" : \"bar\" }\n\t}\n]",
					"options": {
						"raw": {
							"language": "json"
						}
					}
				},
				"url": {
					"raw": "{{URL}}/admin/tenants",
					"host": [
						"{{URL}}"
					],
					"path": [
						"admin",
						"tenants"
					]
				}
			},
			"response": []
        },
        {
			"name": "REST - admin/tenants/paginate",
			"protocolProfileBehavior": {
				"disableBodyPruning": true
			},
			"request": {
				"method": "GET",
				"header": [
					{
						"key": "Content-Type",
						"name": "Content-Type",
						"type": "text",
						"value": "application/json"
					}
				],
				"body": {
					"mode": "raw",
					"raw": "{\n\t\"query\":\n\t[\n\t\t{\n\t\t\t\"command\": \"OFFSET\",\n\t\t\t\"value\": 0\n\t\t},\n\t\t{\n\t\t\t\"command\": \"LIMIT\",\n\t\t\t\"value\": 10\n\t\t}\n\t]\n}",
					"options": {
						"raw": {
							"language": "json"
						}
					}
				},
				"url": {
					"raw": "{{URL}}/admin/tenants/paginate",
					"host": [
						"{{URL}}"
					],
					"path": [
						"admin",
                        "tenants",
                        "paginate"
					]
				}
			},
			"response": []
        },
        {
			"name": "REST - admin/tenants",
			"protocolProfileBehavior": {
				"disableBodyPruning": true
			},
			"request": {
				"method": "GET",
				"header": [
					{
						"key": "Content-Type",
						"name": "Content-Type",
						"type": "text",
						"value": "application/json"
					}
				],
				"body": {
					"mode": "raw",
					"raw": "{\n\t\"query\":\n\t[\n\t\t{\n\t\t\t\"command\": \"WHERE\",\n\t\t\t\"column\": \"id\",\n\t\t\t\"operator\": \"EQUALS\",\n\t\t\t\"value\": \"6861ce3e-6eb2-4eb9-8ef3-44543f0adfe7\"\n\t\t}\n\t]\n}",
					"options": {
						"raw": {
							"language": "json"
						}
					}
				},
				"url": {
					"raw": "{{URL}}/admin/tenants",
					"host": [
						"{{URL}}"
					],
					"path": [
						"admin",
						"tenants"
					]
				}
			},
			"response": []
        },
        {
			"name": "REST - admin/tenant",
			"protocolProfileBehavior": {
				"disableBodyPruning": true
			},
			"request": {
				"method": "GET",
				"header": [
					{
						"key": "Content-Type",
						"name": "Content-Type",
						"type": "text",
						"value": "application/json"
					}
				],
				"body": {
					"mode": "raw",
					"raw": "{\n\t\"query\":\n\t[\n\t\t{\n\t\t\t\"command\": \"WHERE\",\n\t\t\t\"column\": \"id\",\n\t\t\t\"operator\": \"EQUALS\",\n\t\t\t\"value\": \"6861ce3e-6eb2-4eb9-8ef3-44543f0adfe7\"\n\t\t}\n\t]\n}",
					"options": {
						"raw": {
							"language": "json"
						}
					}
				},
				"url": {
					"raw": "{{URL}}/admin/tenant",
					"host": [
						"{{URL}}"
					],
					"path": [
						"admin",
						"tenant"
					]
				}
			},
			"response": []
        },
        {
			"name": "REST - admin/tenant/{id}",
			"protocolProfileBehavior": {
				"disableBodyPruning": true
			},
			"request": {
				"method": "GET",
				"header": [
					{
						"key": "Content-Type",
						"name": "Content-Type",
						"type": "text",
						"value": "application/json"
					}
				],
				"body": {
					"mode": "raw",
					"raw": "",
					"options": {
						"raw": {
							"language": "json"
						}
					}
				},
				"url": {
					"raw": "{{URL}}/admin/tenant/6861ce3e-6eb2-4eb9-8ef3-44543f0adfe7",
					"host": [
						"{{URL}}"
					],
					"path": [
						"admin",
						"tenant",
						"6861ce3e-6eb2-4eb9-8ef3-44543f0adfe7"
					]
				}
			},
			"response": []
        },
        {
			"name": "REST - admin/tenant",
			"request": {
				"method": "PUT",
				"header": [
					{
						"key": "Content-Type",
						"name": "Content-Type",
						"type": "text",
						"value": "application/json"
					}
				],
				"body": {
					"mode": "raw",
					"raw"   : "{\n\t\"id\": \"6861ce3e-6eb2-4eb9-8ef3-44543f0adfe7\", \n\t\"name\": \"6\", \n\t\"code\": \"yu3cl3lwy4nxaf72s2ebnmf7oob9uo5ntp7vncauf3ncdaqeyf\", \n\t\"logo\": \"u\", \n\t\"isActive\": true, \n\t\"data\": { \"foo\" : \"bar\" }\n}",
					"options": {
						"raw": {
							"language": "json"
						}
					}
				},
				"url": {
					"raw": "{{URL}}/admin/tenant",
					"host": [
						"{{URL}}"
					],
					"path": [
						"admin",
						"tenant"
					]
				}
			},
			"response": []
        },
        {
			"name": "REST - admin/tenant/{id}",
			"request": {
				"method": "DELETE",
				"header": [
					{
						"key": "Content-Type",
						"name": "Content-Type",
						"type": "text",
						"value": "application/json"
					}
				],
				"body": {
					"mode": "raw",
					"raw": "",
					"options": {
						"raw": {
							"language": "json"
						}
					}
				},
				"url": {
					"raw": "{{URL}}/admin/tenant/6861ce3e-6eb2-4eb9-8ef3-44543f0adfe7",
					"host": [
						"{{URL}}"
					],
					"path": [
						"admin",
						"tenant",
						"6861ce3e-6eb2-4eb9-8ef3-44543f0adfe7"
					]
				}
			},
			"response": []
		},
        {
			"name": "REST - admin/tenants",
			"request": {
				"method": "DELETE",
				"header": [
					{
						"key": "Content-Type",
						"name": "Content-Type",
						"type": "text",
						"value": "application/json"
					}
				],
				"body": {
					"mode": "raw",
					"raw": "{\n\t\"query\":\n\t[\n\t\t{\n\t\t\t\"command\": \"WHERE\",\n\t\t\t\"column\": \"id\",\n\t\t\t\"operator\": \"CONTAINS\",\n\t\t\t\"value\": \"%%\"\n\t\t}\n\t]\n}",
					"options": {
						"raw": {
							"language": "json"
						}
					}
				},
				"url": {
					"raw": "{{URL}}/admin/tenants",
					"host": [
						"{{URL}}"
					],
					"path": [
						"admin",
						"tenants"
					]
				}
			},
			"response": []
		}
    ],
    "variable": [
		{
			"id": "31c648e9-57c6-4444-8ea1-555dbaaccc66",
			"key": "URL",
			"value": "http://localhost:8080",
			"type": "string"
		}
	]
}