{
    "info": {
		"_postman_id"   : "dbd6b6b8-737d-4899-a873-95db2213ff5f",
		"name"          : "@hades - bplus-it-sappi/channel-overview",
		"schema"        : "https://schema.getpostman.com/json/collection/v2.1.0/collection.json"
    },
    "item": [
        {
			"name": "GraphQL - bplusItSappiCreateChannelOverview",
			"request": {
				"method": "POST",
				"header": [],
				"body": {
					"mode": "graphql",
					"graphql": {
						"query": "mutation ($payload:BplusItSappiCreateChannelOverviewInput!)\n{\n\tbplusItSappiCreateChannelOverview (payload:$payload)\n\t{\n\t\tid\n\t\ttenantId\n\t\ttenantCode\n\t\tsystemId\n\t\tsystemName\n\t\texecutionId\n\t\texecutionType\n\t\texecutionExecutedAt\n\t\texecutionMonitoringStartAt\n\t\texecutionMonitoringEndAt\n\t\terror\n\t\tinactive\n\t\tsuccessful\n\t\tstopped\n\t\tunknown\n\t\tunregistered\n\t\tcreatedAt\n\t\tupdatedAt\n\t}\n}",
						"variables": "{\n\t\"payload\":\n\t{\n\t\t\"id\": \"e483c0ba-8758-493b-8fc2-c4649fcb0f2a\", \n\t\t\"tenantId\": \"1c56f03a-c62d-4233-9d01-1384da5dea11\", \n\t\t\"tenantCode\": \"g32s7fljip5rx4m053m92ae5u40ipdvhsi7i2abo9ghznoqn04\", \n\t\t\"systemId\": \"f51dee00-203a-4efc-b6ce-336414c2943a\", \n\t\t\"systemName\": \"pzh2h75r18oxoqi962yp\", \n\t\t\"executionId\": \"db6388d3-eb59-4ce7-a270-704fdde0eaea\", \n\t\t\"executionType\": \"SUMMARY\", \n\t\t\"executionExecutedAt\": \"2020-07-29 03:00:30\", \n\t\t\"executionMonitoringStartAt\": \"2020-07-29 03:59:15\", \n\t\t\"executionMonitoringEndAt\": \"2020-07-29 12:40:04\", \n\t\t\"error\": 5909800869, \n\t\t\"inactive\": 4104069282, \n\t\t\"successful\": 8051876302, \n\t\t\"stopped\": 1090446846, \n\t\t\"unknown\": 3851873332, \n\t\t\"unregistered\": 5988769152\n\t}\n}"
					}
				},
				"url": {
					"raw": "{{URL}}/graphql",
					"host": [
						"{{URL}}"
					],
					"path": [
						"graphql"
					]
				}
			},
			"response": []
        },
        {
			"name": "GraphQL - bplusItSappiCreateChannelsOverview",
			"request": {
				"method": "POST",
				"header": [],
				"body": {
					"mode": "graphql",
					"graphql": {
						"query": "mutation ($payload:[BplusItSappiCreateChannelOverviewInput]!)\n{\n\tbplusItSappiCreateChannelsOverview (payload:$payload)\n}",
						"variables": "{\n\t\"payload\":\n\t[\n\t\t{\n\t\t\t\"id\": \"2e8f5246-96ad-4136-861d-cbe1a786f58f\", \n\t\t\t\"tenantId\": \"73f1a7c1-722d-49d2-8cb8-3fe79afc3346\", \n\t\t\t\"tenantCode\": \"zhhmjk437q4nn184elv43guyhkva11v0vitl2lpi9qgnkz93kl\", \n\t\t\t\"systemId\": \"6302e55a-fe04-4e44-bca9-466d047462cf\", \n\t\t\t\"systemName\": \"oxtp1bz7opm9xo0uch90\", \n\t\t\t\"executionId\": \"69862db8-d04f-4617-87eb-d47818b54574\", \n\t\t\t\"executionType\": \"SUMMARY\", \n\t\t\t\"executionExecutedAt\": \"2020-07-29 13:16:51\", \n\t\t\t\"executionMonitoringStartAt\": \"2020-07-28 17:49:08\", \n\t\t\t\"executionMonitoringEndAt\": \"2020-07-29 14:27:40\", \n\t\t\t\"error\": 2902374247, \n\t\t\t\"inactive\": 3800446222, \n\t\t\t\"successful\": 4863400306, \n\t\t\t\"stopped\": 7291206608, \n\t\t\t\"unknown\": 8833806641, \n\t\t\t\"unregistered\": 8165090787\n\t\t},\n\t\t{\n\t\t\t\"id\": \"d6b6e55e-5065-495d-bed1-f11ef4222107\", \n\t\t\t\"tenantId\": \"e702a6f1-050d-44dc-a229-4421800866a4\", \n\t\t\t\"tenantCode\": \"evfd9tt06lbkb7hs4kztm0kmxi9xrl4ndiieyw9j6o2ib70d77\", \n\t\t\t\"systemId\": \"46a2a42d-e405-4f37-beee-8db3c577062e\", \n\t\t\t\"systemName\": \"m47zqwwawr0eb57ksm5x\", \n\t\t\t\"executionId\": \"320cdede-3933-4623-bc80-05d77bce1c83\", \n\t\t\t\"executionType\": \"SUMMARY\", \n\t\t\t\"executionExecutedAt\": \"2020-07-29 14:20:12\", \n\t\t\t\"executionMonitoringStartAt\": \"2020-07-28 17:57:47\", \n\t\t\t\"executionMonitoringEndAt\": \"2020-07-28 23:18:25\", \n\t\t\t\"error\": 6333820051, \n\t\t\t\"inactive\": 5330478563, \n\t\t\t\"successful\": 2663543329, \n\t\t\t\"stopped\": 5426294143, \n\t\t\t\"unknown\": 2590925991, \n\t\t\t\"unregistered\": 7502611180\n\t\t},\n\t\t{\n\t\t\t\"id\": \"f21e3374-23e2-453e-8a02-f8644b14d9f5\", \n\t\t\t\"tenantId\": \"aeca567c-eba7-40a6-8579-61544e7ac330\", \n\t\t\t\"tenantCode\": \"m0uwmwtinwj27gjwdera0oq9vdg2vjtaukiurzctmtgsir7tds\", \n\t\t\t\"systemId\": \"b2039be0-c913-40d6-b838-a0a89c8b6974\", \n\t\t\t\"systemName\": \"fyw3tchevm4xv1kqtyhs\", \n\t\t\t\"executionId\": \"d4797ccd-3bc5-477f-be88-f2ae20c12b8c\", \n\t\t\t\"executionType\": \"DETAIL\", \n\t\t\t\"executionExecutedAt\": \"2020-07-29 13:20:56\", \n\t\t\t\"executionMonitoringStartAt\": \"2020-07-28 22:15:56\", \n\t\t\t\"executionMonitoringEndAt\": \"2020-07-29 05:45:50\", \n\t\t\t\"error\": 3111607894, \n\t\t\t\"inactive\": 1991370313, \n\t\t\t\"successful\": 9479540283, \n\t\t\t\"stopped\": 1386344213, \n\t\t\t\"unknown\": 7005533915, \n\t\t\t\"unregistered\": 6257595525\n\t\t},\n\t\t{\n\t\t\t\"id\": \"1e983b01-1005-4b39-b455-f88c0cd6fb8f\", \n\t\t\t\"tenantId\": \"aa39bb9b-6bf2-459d-850b-1bb0062e3f1c\", \n\t\t\t\"tenantCode\": \"gbgiwc9m27okwt1qyti0vhntvze7rmqu73sm3u9fl84vc37pq2\", \n\t\t\t\"systemId\": \"298c42c6-4a92-4419-9678-5ab30c0db9c7\", \n\t\t\t\"systemName\": \"9skw8i75bwbdzdckmows\", \n\t\t\t\"executionId\": \"e8647619-7b86-48a6-a8fe-e1fc4f0ca348\", \n\t\t\t\"executionType\": \"SUMMARY\", \n\t\t\t\"executionExecutedAt\": \"2020-07-28 23:04:48\", \n\t\t\t\"executionMonitoringStartAt\": \"2020-07-28 17:40:30\", \n\t\t\t\"executionMonitoringEndAt\": \"2020-07-29 02:48:37\", \n\t\t\t\"error\": 4633453888, \n\t\t\t\"inactive\": 7898606972, \n\t\t\t\"successful\": 2181203556, \n\t\t\t\"stopped\": 8100521988, \n\t\t\t\"unknown\": 5956386868, \n\t\t\t\"unregistered\": 4451965615\n\t\t},\n\t\t{\n\t\t\t\"id\": \"2621d651-76e8-415b-a219-d9331a0875b0\", \n\t\t\t\"tenantId\": \"88f2d39f-5579-43dc-ab29-81f89cd94065\", \n\t\t\t\"tenantCode\": \"9204bx9oeqsjuunhniuwjlu32qo7awygc70qcf5fedk84z3t8e\", \n\t\t\t\"systemId\": \"03b71e36-0c8b-4783-b048-bb5227d7330a\", \n\t\t\t\"systemName\": \"8l6d6j8lv43aykmlgw70\", \n\t\t\t\"executionId\": \"d335215f-6615-401a-8f86-eee6b3510526\", \n\t\t\t\"executionType\": \"DETAIL\", \n\t\t\t\"executionExecutedAt\": \"2020-07-29 06:37:11\", \n\t\t\t\"executionMonitoringStartAt\": \"2020-07-29 03:55:56\", \n\t\t\t\"executionMonitoringEndAt\": \"2020-07-29 14:59:40\", \n\t\t\t\"error\": 1773398110, \n\t\t\t\"inactive\": 6167116168, \n\t\t\t\"successful\": 9754212549, \n\t\t\t\"stopped\": 8558859544, \n\t\t\t\"unknown\": 5404382816, \n\t\t\t\"unregistered\": 1383884864\n\t\t},\n\t\t{\n\t\t\t\"id\": \"4e00c3b3-8029-423f-aafa-13d568e47bc1\", \n\t\t\t\"tenantId\": \"3e5dd182-910f-414a-9613-e0a0f612a5b0\", \n\t\t\t\"tenantCode\": \"jcrv4cufh98f4lhxzv7o547gujqnb0e97mtmo155aavccuz9bb\", \n\t\t\t\"systemId\": \"e1178e9f-4568-481a-b6e8-43b7ee31d1cd\", \n\t\t\t\"systemName\": \"ky21e6m64be417xo143y\", \n\t\t\t\"executionId\": \"8bfcffaa-18d5-4196-849b-dc6411ac77a0\", \n\t\t\t\"executionType\": \"SUMMARY\", \n\t\t\t\"executionExecutedAt\": \"2020-07-29 05:46:53\", \n\t\t\t\"executionMonitoringStartAt\": \"2020-07-29 05:34:30\", \n\t\t\t\"executionMonitoringEndAt\": \"2020-07-29 10:07:14\", \n\t\t\t\"error\": 3447176560, \n\t\t\t\"inactive\": 7071595794, \n\t\t\t\"successful\": 9966626975, \n\t\t\t\"stopped\": 1192360883, \n\t\t\t\"unknown\": 9850747950, \n\t\t\t\"unregistered\": 5343310199\n\t\t},\n\t\t{\n\t\t\t\"id\": \"7a51fae4-c59a-40ea-97ee-100a06f8206b\", \n\t\t\t\"tenantId\": \"b13dcfa8-2a3f-4b0c-9161-462dc0893a29\", \n\t\t\t\"tenantCode\": \"h0gvfaol9l0go60j7v3607ocmr788n9c6b3f32ig0i1d4hwfjr\", \n\t\t\t\"systemId\": \"9eb7d78d-6b2e-41bb-b392-b8e79a62fae7\", \n\t\t\t\"systemName\": \"g431a6114m6nlzsm9bpp\", \n\t\t\t\"executionId\": \"fdbed449-b6df-4a0f-a2d6-60ff249e2b48\", \n\t\t\t\"executionType\": \"DETAIL\", \n\t\t\t\"executionExecutedAt\": \"2020-07-29 05:34:29\", \n\t\t\t\"executionMonitoringStartAt\": \"2020-07-29 15:46:16\", \n\t\t\t\"executionMonitoringEndAt\": \"2020-07-29 02:30:51\", \n\t\t\t\"error\": 3524758533, \n\t\t\t\"inactive\": 4954632203, \n\t\t\t\"successful\": 8753900321, \n\t\t\t\"stopped\": 3325265931, \n\t\t\t\"unknown\": 3255393245, \n\t\t\t\"unregistered\": 7971373188\n\t\t},\n\t\t{\n\t\t\t\"id\": \"6f9242cd-e112-4ab8-bcb6-d60fb7665348\", \n\t\t\t\"tenantId\": \"10e52cba-2e06-4295-a0ab-ea01712fac0f\", \n\t\t\t\"tenantCode\": \"gtojizw4870mr5lt3f9ek7j90adsny4k4frm3yboodn2pb2ply\", \n\t\t\t\"systemId\": \"53fa810a-bf9a-43c0-b453-e3a2cbb16918\", \n\t\t\t\"systemName\": \"n0r0m982j2b8les6mer7\", \n\t\t\t\"executionId\": \"479e5e6d-6871-4f70-95bb-27f764f0bd8d\", \n\t\t\t\"executionType\": \"DETAIL\", \n\t\t\t\"executionExecutedAt\": \"2020-07-29 00:09:32\", \n\t\t\t\"executionMonitoringStartAt\": \"2020-07-29 06:07:37\", \n\t\t\t\"executionMonitoringEndAt\": \"2020-07-28 18:55:34\", \n\t\t\t\"error\": 8349759541, \n\t\t\t\"inactive\": 4195287419, \n\t\t\t\"successful\": 1871124169, \n\t\t\t\"stopped\": 3433802157, \n\t\t\t\"unknown\": 8836266232, \n\t\t\t\"unregistered\": 1372985375\n\t\t},\n\t\t{\n\t\t\t\"id\": \"f216f70b-66d9-466e-95f2-133d882c647e\", \n\t\t\t\"tenantId\": \"db6214fe-a0d8-4fae-9d75-6e4d1caba852\", \n\t\t\t\"tenantCode\": \"j4y3mhkqblylz6o6rxjocxmv4yenr465dx7w9c3nkn55k0olqg\", \n\t\t\t\"systemId\": \"f1316369-d547-4dc3-848b-31fe38b7081a\", \n\t\t\t\"systemName\": \"nuvcwhxxeiwz87dculbh\", \n\t\t\t\"executionId\": \"1fe71edc-f679-4459-95f7-24fe5e7fde9c\", \n\t\t\t\"executionType\": \"DETAIL\", \n\t\t\t\"executionExecutedAt\": \"2020-07-29 10:12:00\", \n\t\t\t\"executionMonitoringStartAt\": \"2020-07-29 05:22:07\", \n\t\t\t\"executionMonitoringEndAt\": \"2020-07-28 16:37:02\", \n\t\t\t\"error\": 6971147439, \n\t\t\t\"inactive\": 7829345746, \n\t\t\t\"successful\": 1035637348, \n\t\t\t\"stopped\": 2082379554, \n\t\t\t\"unknown\": 7101410420, \n\t\t\t\"unregistered\": 1710800038\n\t\t},\n\t\t{\n\t\t\t\"id\": \"0cd55c6f-7feb-4211-98b3-16983ead3491\", \n\t\t\t\"tenantId\": \"18bedcae-4cf2-4af8-bd20-04b39b213b76\", \n\t\t\t\"tenantCode\": \"mfme7llc8ie3w44q4fuo6pqpqj420vtp22itvdzm8ydvwx66ac\", \n\t\t\t\"systemId\": \"c4fdedbb-e25e-46b2-8f13-6b2ed3c5f59f\", \n\t\t\t\"systemName\": \"59stf7h2vajkg936in9e\", \n\t\t\t\"executionId\": \"e416e36f-08c0-4859-9696-0db2afd5c2dd\", \n\t\t\t\"executionType\": \"SUMMARY\", \n\t\t\t\"executionExecutedAt\": \"2020-07-28 16:50:34\", \n\t\t\t\"executionMonitoringStartAt\": \"2020-07-29 14:06:06\", \n\t\t\t\"executionMonitoringEndAt\": \"2020-07-29 09:10:12\", \n\t\t\t\"error\": 6796786387, \n\t\t\t\"inactive\": 4640856978, \n\t\t\t\"successful\": 8834097510, \n\t\t\t\"stopped\": 8157880787, \n\t\t\t\"unknown\": 6171319928, \n\t\t\t\"unregistered\": 4314457206\n\t\t},\n\t\t{\n\t\t\t\"id\": \"67ae235b-8092-433a-a3f6-4796c46958f0\", \n\t\t\t\"tenantId\": \"0c74966a-6f42-428e-9df2-0cb003591e88\", \n\t\t\t\"tenantCode\": \"962bxj3mmrcxt78xr98fs0gqgspsjfw5rlhcjdnfrsp9l7smb2\", \n\t\t\t\"systemId\": \"8944a5f9-ed08-47d0-8aaa-8d45a3dd9028\", \n\t\t\t\"systemName\": \"iyzuu504119rifhcbjak\", \n\t\t\t\"executionId\": \"8527aadd-b46c-4d8a-8d65-7bf04897722c\", \n\t\t\t\"executionType\": \"SUMMARY\", \n\t\t\t\"executionExecutedAt\": \"2020-07-28 22:47:04\", \n\t\t\t\"executionMonitoringStartAt\": \"2020-07-29 01:31:05\", \n\t\t\t\"executionMonitoringEndAt\": \"2020-07-29 01:29:56\", \n\t\t\t\"error\": 2190867801, \n\t\t\t\"inactive\": 3162721970, \n\t\t\t\"successful\": 7042355664, \n\t\t\t\"stopped\": 5662700732, \n\t\t\t\"unknown\": 1106684513, \n\t\t\t\"unregistered\": 3937793309\n\t\t},\n\t\t{\n\t\t\t\"id\": \"8998fd06-b05d-494e-a702-c14e2575cdfc\", \n\t\t\t\"tenantId\": \"d81c72ed-9f1a-4c19-a8ca-744583378288\", \n\t\t\t\"tenantCode\": \"lhuif1knqwe6gbeeyssc0pag4zzhrxzzv7wkka670emgsj480f\", \n\t\t\t\"systemId\": \"ca0e7956-6fde-4df3-aaea-ee9ee2d10798\", \n\t\t\t\"systemName\": \"xep8dsy6jtj4onfqxk6l\", \n\t\t\t\"executionId\": \"17235d78-bf14-4d66-8ad5-cf159fed84ac\", \n\t\t\t\"executionType\": \"SUMMARY\", \n\t\t\t\"executionExecutedAt\": \"2020-07-29 12:11:37\", \n\t\t\t\"executionMonitoringStartAt\": \"2020-07-29 13:08:00\", \n\t\t\t\"executionMonitoringEndAt\": \"2020-07-29 05:02:53\", \n\t\t\t\"error\": 7165057188, \n\t\t\t\"inactive\": 3483481905, \n\t\t\t\"successful\": 2639673830, \n\t\t\t\"stopped\": 5327370961, \n\t\t\t\"unknown\": 6207074023, \n\t\t\t\"unregistered\": 1578111527\n\t\t},\n\t\t{\n\t\t\t\"id\": \"efdeafa8-b0d3-4384-8f10-58f4f3c6fb29\", \n\t\t\t\"tenantId\": \"6b2ec6c0-7ad2-41aa-bb81-ee5ed446fcae\", \n\t\t\t\"tenantCode\": \"ccoynfntbo90ck2zz7990r2ghdewt7jnwdulnzd0w4jya7oqjc\", \n\t\t\t\"systemId\": \"bec28a55-8067-423f-8d65-e1568d180680\", \n\t\t\t\"systemName\": \"xcz296l8wm6rpdtj8jyg\", \n\t\t\t\"executionId\": \"3ccc9d84-8f49-48cf-960a-9db614ae6c83\", \n\t\t\t\"executionType\": \"SUMMARY\", \n\t\t\t\"executionExecutedAt\": \"2020-07-29 09:14:44\", \n\t\t\t\"executionMonitoringStartAt\": \"2020-07-29 00:27:47\", \n\t\t\t\"executionMonitoringEndAt\": \"2020-07-29 04:30:43\", \n\t\t\t\"error\": 8613727684, \n\t\t\t\"inactive\": 8476421906, \n\t\t\t\"successful\": 5443971278, \n\t\t\t\"stopped\": 4692990646, \n\t\t\t\"unknown\": 1854272906, \n\t\t\t\"unregistered\": 3657498606\n\t\t},\n\t\t{\n\t\t\t\"id\": \"6735d5b6-e568-4a29-b4e9-f498709fd64f\", \n\t\t\t\"tenantId\": \"94cab589-149c-4d9e-b966-cc41e6aa1314\", \n\t\t\t\"tenantCode\": \"irj2vec7m86h8q96xdgotfwi83vcfchddwbk2gxagqhtlbe17n\", \n\t\t\t\"systemId\": \"33ef601b-58ed-4e5c-8fab-ca713c174c72\", \n\t\t\t\"systemName\": \"gyjpbdlg8838mdmc1ip5\", \n\t\t\t\"executionId\": \"1a30fdda-e7b4-41a2-b1ac-2d8355dc0212\", \n\t\t\t\"executionType\": \"DETAIL\", \n\t\t\t\"executionExecutedAt\": \"2020-07-29 08:46:05\", \n\t\t\t\"executionMonitoringStartAt\": \"2020-07-28 23:47:32\", \n\t\t\t\"executionMonitoringEndAt\": \"2020-07-29 15:16:47\", \n\t\t\t\"error\": 7744452904, \n\t\t\t\"inactive\": 6052144507, \n\t\t\t\"successful\": 3098179509, \n\t\t\t\"stopped\": 8539981777, \n\t\t\t\"unknown\": 1350065710, \n\t\t\t\"unregistered\": 4163236943\n\t\t},\n\t\t{\n\t\t\t\"id\": \"c9c9ee80-b708-4326-9faa-1317b4ab7264\", \n\t\t\t\"tenantId\": \"e4e921e2-17e7-4b1f-ae50-375516340f65\", \n\t\t\t\"tenantCode\": \"kgrq0dafhk8rdh9byedzh5rdkcpy0k9q36ahv8q66cm6n8ree7\", \n\t\t\t\"systemId\": \"3b6d3ef5-b527-461a-9baf-486d9df6edbd\", \n\t\t\t\"systemName\": \"24730irtp4sypjdo5bqd\", \n\t\t\t\"executionId\": \"7d999e17-ab3c-4221-be67-0ae5e3318386\", \n\t\t\t\"executionType\": \"SUMMARY\", \n\t\t\t\"executionExecutedAt\": \"2020-07-28 20:54:44\", \n\t\t\t\"executionMonitoringStartAt\": \"2020-07-29 08:06:10\", \n\t\t\t\"executionMonitoringEndAt\": \"2020-07-28 17:17:50\", \n\t\t\t\"error\": 3122222636, \n\t\t\t\"inactive\": 6577352433, \n\t\t\t\"successful\": 5915816598, \n\t\t\t\"stopped\": 5576283731, \n\t\t\t\"unknown\": 7953688881, \n\t\t\t\"unregistered\": 6899233207\n\t\t},\n\t\t{\n\t\t\t\"id\": \"e9792fa3-3390-4ed3-8a0b-31cbc913d89c\", \n\t\t\t\"tenantId\": \"d0c7c476-a908-4905-88ef-b631c9da46c9\", \n\t\t\t\"tenantCode\": \"da2kzqtxztwn2suvjv3ridbs1z2n7ih66013qaasrn2gjruxg2\", \n\t\t\t\"systemId\": \"04cb26fa-499c-4d10-ada5-2cfa13ca276f\", \n\t\t\t\"systemName\": \"ccf1wf3xyeeu488pqw61\", \n\t\t\t\"executionId\": \"dccfa053-67d2-4e85-b9aa-e48fa45192bd\", \n\t\t\t\"executionType\": \"DETAIL\", \n\t\t\t\"executionExecutedAt\": \"2020-07-28 20:10:09\", \n\t\t\t\"executionMonitoringStartAt\": \"2020-07-29 00:19:04\", \n\t\t\t\"executionMonitoringEndAt\": \"2020-07-29 04:10:37\", \n\t\t\t\"error\": 8988977617, \n\t\t\t\"inactive\": 8759885678, \n\t\t\t\"successful\": 7025238780, \n\t\t\t\"stopped\": 5898580536, \n\t\t\t\"unknown\": 6464773128, \n\t\t\t\"unregistered\": 8151134933\n\t\t},\n\t\t{\n\t\t\t\"id\": \"977c7b91-1d67-485d-aef6-14a090d6f1e9\", \n\t\t\t\"tenantId\": \"d59ca8b7-be56-4be6-9982-8d7ce778f51f\", \n\t\t\t\"tenantCode\": \"5ddxndjg9ztz71l2qraayfs7p8wv2roefg0v888pavx1vn78s3\", \n\t\t\t\"systemId\": \"a7c39c34-b152-4934-a0f7-a74799edd3c5\", \n\t\t\t\"systemName\": \"ihlvvor1ozq5wnd79xks\", \n\t\t\t\"executionId\": \"c46544d3-e44c-4930-b4ee-a1f0d770e9df\", \n\t\t\t\"executionType\": \"SUMMARY\", \n\t\t\t\"executionExecutedAt\": \"2020-07-29 06:28:40\", \n\t\t\t\"executionMonitoringStartAt\": \"2020-07-29 12:47:23\", \n\t\t\t\"executionMonitoringEndAt\": \"2020-07-29 11:58:28\", \n\t\t\t\"error\": 5181829353, \n\t\t\t\"inactive\": 1942774280, \n\t\t\t\"successful\": 6691244987, \n\t\t\t\"stopped\": 1995063768, \n\t\t\t\"unknown\": 4167226332, \n\t\t\t\"unregistered\": 3804728071\n\t\t},\n\t\t{\n\t\t\t\"id\": \"213c16f9-5aa6-4db4-b021-c44341388f01\", \n\t\t\t\"tenantId\": \"9b97556c-7cef-491f-afeb-e1fe2b2c694a\", \n\t\t\t\"tenantCode\": \"fnhmkeqvfaj08bx7fkz1wpbdim4tjkznljwvabj8a888lxwu0w\", \n\t\t\t\"systemId\": \"63d619f8-d72f-4d60-aa8d-b1f4f203000d\", \n\t\t\t\"systemName\": \"y3mnpr1ibaawzii6w7kd\", \n\t\t\t\"executionId\": \"7077e681-7d95-44f0-99fb-481d7cd1f89f\", \n\t\t\t\"executionType\": \"DETAIL\", \n\t\t\t\"executionExecutedAt\": \"2020-07-28 16:53:02\", \n\t\t\t\"executionMonitoringStartAt\": \"2020-07-28 16:59:16\", \n\t\t\t\"executionMonitoringEndAt\": \"2020-07-29 08:57:20\", \n\t\t\t\"error\": 9084396674, \n\t\t\t\"inactive\": 3795203305, \n\t\t\t\"successful\": 5140502317, \n\t\t\t\"stopped\": 6221016066, \n\t\t\t\"unknown\": 4457651210, \n\t\t\t\"unregistered\": 2286935495\n\t\t},\n\t\t{\n\t\t\t\"id\": \"8c30d252-37f4-4e3a-9b48-615b9e3c0ccf\", \n\t\t\t\"tenantId\": \"a798479e-7c43-4ce0-b57e-208200205570\", \n\t\t\t\"tenantCode\": \"pb7pc4xpjq7masastasvxtfwm1nyqidf5hdb58jbvfotx1tkk9\", \n\t\t\t\"systemId\": \"3e22b1f2-5621-4e82-bceb-1543d4f87540\", \n\t\t\t\"systemName\": \"t5kc4lsjnf8d4y99gmbm\", \n\t\t\t\"executionId\": \"b4f112b4-bdeb-48e0-96f1-c263f1470608\", \n\t\t\t\"executionType\": \"DETAIL\", \n\t\t\t\"executionExecutedAt\": \"2020-07-28 19:44:51\", \n\t\t\t\"executionMonitoringStartAt\": \"2020-07-29 10:16:53\", \n\t\t\t\"executionMonitoringEndAt\": \"2020-07-29 01:41:12\", \n\t\t\t\"error\": 6044719993, \n\t\t\t\"inactive\": 3367268337, \n\t\t\t\"successful\": 9252817146, \n\t\t\t\"stopped\": 6972481250, \n\t\t\t\"unknown\": 7951521365, \n\t\t\t\"unregistered\": 2815223976\n\t\t},\n\t\t{\n\t\t\t\"id\": \"83b92024-401e-451c-8fed-66aa98ce59e2\", \n\t\t\t\"tenantId\": \"0b61e1a8-5926-4e83-93da-5e3addb5f351\", \n\t\t\t\"tenantCode\": \"ov2moo4lt5mz0xxp7kylz5jqnj4xzl5iqaz28z97oepjm40t7j\", \n\t\t\t\"systemId\": \"667a66ce-fbd2-4008-8438-da6edf620970\", \n\t\t\t\"systemName\": \"vqydmnlt7ntc3taqri96\", \n\t\t\t\"executionId\": \"568c2cb1-2f50-48c0-a5f7-a064f1fed401\", \n\t\t\t\"executionType\": \"DETAIL\", \n\t\t\t\"executionExecutedAt\": \"2020-07-29 14:14:10\", \n\t\t\t\"executionMonitoringStartAt\": \"2020-07-29 11:02:44\", \n\t\t\t\"executionMonitoringEndAt\": \"2020-07-28 22:50:29\", \n\t\t\t\"error\": 5739309410, \n\t\t\t\"inactive\": 5213823823, \n\t\t\t\"successful\": 6424152347, \n\t\t\t\"stopped\": 6951322128, \n\t\t\t\"unknown\": 8250915396, \n\t\t\t\"unregistered\": 6150841194\n\t\t}\n\t]\n}"
					}
				},
				"url": {
					"raw": "{{URL}}/graphql",
					"host": [
						"{{URL}}"
					],
					"path": [
						"graphql"
					]
				}
			},
			"response": []
        },
        {
			"name": "GraphQL - bplusItSappiPaginateChannelsOverview",
			"request": {
				"method": "POST",
				"header": [],
				"body": {
					"mode": "graphql",
					"graphql": {
						"query": "query ($query:[QueryStatementInput] $constraint:[QueryStatementInput])\n{\n\tbplusItSappiPaginateChannelsOverview (query:$query constraint:$constraint)\n\t{\n\t\ttotal\n\t\tcount\n\t\trows\n\t}\n}",
						"variables": "{\n\t\"query\":\n\t[\n\t\t{\n\t\t\t\"command\": \"OFFSET\",\n\t\t\t\"value\": 0\n\t\t},\n\t\t{\n\t\t\t\"command\": \"LIMIT\",\n\t\t\t\"value\": 10\n\t\t}\n\t]\n}"
					}
				},
				"url": {
					"raw": "{{URL}}/graphql",
					"host": [
						"{{URL}}"
					],
					"path": [
						"graphql"
					]
				}
			},
			"response": []
        },
        {
			"name": "GraphQL - bplusItSappiGetChannelsOverview",
			"request": {
				"method": "POST",
				"header": [],
				"body": {
					"mode": "graphql",
					"graphql": {
						"query": "query ($query:[QueryStatementInput])\n{\n\tbplusItSappiGetChannelsOverview (query: $query)\n\t{\n\t\tid\n\t\ttenantId\n\t\ttenantCode\n\t\tsystemId\n\t\tsystemName\n\t\texecutionId\n\t\texecutionType\n\t\texecutionExecutedAt\n\t\texecutionMonitoringStartAt\n\t\texecutionMonitoringEndAt\n\t\terror\n\t\tinactive\n\t\tsuccessful\n\t\tstopped\n\t\tunknown\n\t\tunregistered\n\t\tcreatedAt\n\t\tupdatedAt\n\t}\n}",
						"variables": "{\n\t\"query\":\n\t[\n\t\t{\n\t\t\t\"command\": \"WHERE\",\n\t\t\t\"column\": \"id\",\n\t\t\t\"operator\": \"EQUALS\",\n\t\t\t\"value\": \"e483c0ba-8758-493b-8fc2-c4649fcb0f2a\"\n\t\t}\n\t]\n}"
					}
				},
				"url": {
					"raw": "{{URL}}/graphql",
					"host": [
						"{{URL}}"
					],
					"path": [
						"graphql"
					]
				}
			},
			"response": []
        },
        {
			"name": "GraphQL - bplusItSappiFindChannelOverview",
			"request": {
				"method": "POST",
				"header": [],
				"body": {
					"mode": "graphql",
					"graphql": {
						"query": "query ($query:[QueryStatementInput])\n{\n\tbplusItSappiFindChannelOverview (query: $query)\n\t{\n\t\tid\n\t\ttenantId\n\t\ttenantCode\n\t\tsystemId\n\t\tsystemName\n\t\texecutionId\n\t\texecutionType\n\t\texecutionExecutedAt\n\t\texecutionMonitoringStartAt\n\t\texecutionMonitoringEndAt\n\t\terror\n\t\tinactive\n\t\tsuccessful\n\t\tstopped\n\t\tunknown\n\t\tunregistered\n\t\tcreatedAt\n\t\tupdatedAt\n\t}\n}",
						"variables": "{\n\t\"query\":\n\t[\n\t\t{\n\t\t\t\"command\": \"WHERE\",\n\t\t\t\"column\": \"id\",\n\t\t\t\"operator\": \"EQUALS\",\n\t\t\t\"value\": \"e483c0ba-8758-493b-8fc2-c4649fcb0f2a\"\n\t\t}\n\t]\n}"
					}
				},
				"url": {
					"raw": "{{URL}}/graphql",
					"host": [
						"{{URL}}"
					],
					"path": [
						"graphql"
					]
				}
			},
			"response": []
        },
        {
			"name": "GraphQL - bplusItSappiFindChannelOverviewById",
			"request": {
				"method": "POST",
				"header": [],
				"body": {
					"mode": "graphql",
					"graphql": {
						"query": "query ($id:ID)\n{\n\tbplusItSappiFindChannelOverviewById (id:$id)\n\t{\n\t\tid\n\t\ttenantId\n\t\ttenantCode\n\t\tsystemId\n\t\tsystemName\n\t\texecutionId\n\t\texecutionType\n\t\texecutionExecutedAt\n\t\texecutionMonitoringStartAt\n\t\texecutionMonitoringEndAt\n\t\terror\n\t\tinactive\n\t\tsuccessful\n\t\tstopped\n\t\tunknown\n\t\tunregistered\n\t\tcreatedAt\n\t\tupdatedAt\n\t}\n}",
						"variables": "{\n\t\"id\": \"e483c0ba-8758-493b-8fc2-c4649fcb0f2a\"\n}"
					}
				},
				"url": {
					"raw": "{{URL}}/graphql",
					"host": [
						"{{URL}}"
					],
					"path": [
						"graphql"
					]
				}
			},
			"response": []
        },
        {
			"name": "GraphQL - bplusItSappiUpdateChannelOverview",
			"request": {
				"method": "POST",
				"header": [],
				"body": {
					"mode": "graphql",
					"graphql": {
						"query": "mutation ($payload:BplusItSappiUpdateChannelOverviewInput!)\n{\n\tbplusItSappiUpdateChannelOverview (payload:$payload)\n\t{\n\t\tid\n\t\ttenantId\n\t\ttenantCode\n\t\tsystemId\n\t\tsystemName\n\t\texecutionId\n\t\texecutionType\n\t\texecutionExecutedAt\n\t\texecutionMonitoringStartAt\n\t\texecutionMonitoringEndAt\n\t\terror\n\t\tinactive\n\t\tsuccessful\n\t\tstopped\n\t\tunknown\n\t\tunregistered\n\t\tcreatedAt\n\t\tupdatedAt\n\t}\n}",
						"variables": "{\n\t\"payload\":\n\t{\n\t\t\"id\": \"e483c0ba-8758-493b-8fc2-c4649fcb0f2a\", \n\t\t\"tenantId\": \"1c56f03a-c62d-4233-9d01-1384da5dea11\", \n\t\t\"tenantCode\": \"hkr46d7cxiqex4edgvukelufgahi429a8c99hfocq3unrhom4j\", \n\t\t\"systemId\": \"f51dee00-203a-4efc-b6ce-336414c2943a\", \n\t\t\"systemName\": \"f084f0u2xu5p9896d5o3\", \n\t\t\"executionId\": \"db6388d3-eb59-4ce7-a270-704fdde0eaea\", \n\t\t\"executionType\": \"DETAIL\", \n\t\t\"executionExecutedAt\": \"2020-07-28 22:19:10\", \n\t\t\"executionMonitoringStartAt\": \"2020-07-29 06:47:38\", \n\t\t\"executionMonitoringEndAt\": \"2020-07-29 11:26:05\", \n\t\t\"error\": 2599682821, \n\t\t\"inactive\": 1706185474, \n\t\t\"successful\": 7109969760, \n\t\t\"stopped\": 4173741936, \n\t\t\"unknown\": 7324384141, \n\t\t\"unregistered\": 1291630022\n\t}\n}"
					}
				},
				"url": {
					"raw": "{{URL}}/graphql",
					"host": [
						"{{URL}}"
					],
					"path": [
						"graphql"
					]
				}
			},
			"response": []
        },
        {
			"name": "GraphQL - bplusItSappiDeleteChannelOverviewById",
			"request": {
				"method": "POST",
				"header": [],
				"body": {
					"mode": "graphql",
					"graphql": {
						"query": "mutation ($id:ID!)\n{\n\tbplusItSappiDeleteChannelOverviewById (id:$id)\n\t{\n\t\tid\n\t\ttenantId\n\t\ttenantCode\n\t\tsystemId\n\t\tsystemName\n\t\texecutionId\n\t\texecutionType\n\t\texecutionExecutedAt\n\t\texecutionMonitoringStartAt\n\t\texecutionMonitoringEndAt\n\t\terror\n\t\tinactive\n\t\tsuccessful\n\t\tstopped\n\t\tunknown\n\t\tunregistered\n\t\tcreatedAt\n\t\tupdatedAt\n\t}\n}",
						"variables": "{\n\t\"id\": \"e483c0ba-8758-493b-8fc2-c4649fcb0f2a\"\n}"
					}
				},
				"url": {
					"raw": "{{URL}}/graphql",
					"host": [
						"{{URL}}"
					],
					"path": [
						"graphql"
					]
				}
			},
			"response": []
        },
        {
			"name": "GraphQL - bplusItSappiDeleteChannelsOverview",
			"request": {
				"method": "POST",
				"header": [],
				"body": {
					"mode": "graphql",
					"graphql": {
						"query": "mutation ($query:[QueryStatementInput])\n{\n\tbplusItSappiDeleteChannelsOverview (query: $query)\n\t{\n\t\tid\n\t\ttenantId\n\t\ttenantCode\n\t\tsystemId\n\t\tsystemName\n\t\texecutionId\n\t\texecutionType\n\t\texecutionExecutedAt\n\t\texecutionMonitoringStartAt\n\t\texecutionMonitoringEndAt\n\t\terror\n\t\tinactive\n\t\tsuccessful\n\t\tstopped\n\t\tunknown\n\t\tunregistered\n\t\tcreatedAt\n\t\tupdatedAt\n\t}\n}",
						"variables": "{\n\t\"query\":\n\t[\n\t\t{\n\t\t\t\"command\": \"WHERE\",\n\t\t\t\"column\": \"id\",\n\t\t\t\"operator\": \"CONTAINS\",\n\t\t\t\"value\": \"%%\"\n\t\t}\n\t]\n}"
					}
				},
				"url": {
					"raw": "{{URL}}/graphql",
					"host": [
						"{{URL}}"
					],
					"path": [
						"graphql"
					]
				}
			},
			"response": []
        },
        {
			"name": "REST - bplus-it-sappi/channel-overview",
			"request": {
				"method": "POST",
				"header": [
					{
						"key"   : "Content-Type",
						"name"  : "Content-Type",
						"type"  : "text",
						"value" : "application/json"
					}
				],
				"body": {
					"mode"  : "raw",
					"raw"   : "{\n\t\"id\": \"e483c0ba-8758-493b-8fc2-c4649fcb0f2a\", \n\t\"tenantId\": \"1c56f03a-c62d-4233-9d01-1384da5dea11\", \n\t\"tenantCode\": \"5i25e4aq5v076jn3nhxzhqqlulhy79f4yuvjd9k2jy0uvqxvjb\", \n\t\"systemId\": \"f51dee00-203a-4efc-b6ce-336414c2943a\", \n\t\"systemName\": \"oloe3ro9szmt2xi1r1xj\", \n\t\"executionId\": \"db6388d3-eb59-4ce7-a270-704fdde0eaea\", \n\t\"executionType\": \"DETAIL\", \n\t\"executionExecutedAt\": \"2020-07-28 18:40:34\", \n\t\"executionMonitoringStartAt\": \"2020-07-29 04:52:43\", \n\t\"executionMonitoringEndAt\": \"2020-07-29 09:46:26\", \n\t\"error\": 1205074906, \n\t\"inactive\": 4541666397, \n\t\"successful\": 3287098305, \n\t\"stopped\": 6800567215, \n\t\"unknown\": 3624128122, \n\t\"unregistered\": 8039843958\n}",
					"options": {
						"raw": {
							"language": "json"
						}
					}
				},
				"url": {
					"raw": "{{URL}}/bplus-it-sappi/channel-overview",
					"host": [
						"{{URL}}"
					],
					"path": [
						"bplus-it-sappi",
						"channel-overview"
					]
				}
			},
			"response": []
        },
        {
			"name": "REST - bplus-it-sappi/channels-overview",
			"request": {
				"method": "POST",
				"header": [
					{
						"key"   : "Content-Type",
						"name"  : "Content-Type",
						"type"  : "text",
						"value" : "application/json"
					}
				],
				"body": {
					"mode"  : "raw",
					"raw"   : "[\n\t{\n\t\t\"id\": \"10b914c1-e3e2-40f5-a24e-b4cb04217e19\", \n\t\t\"tenantId\": \"8d9b324f-6da2-43d9-a5e0-33bffeebd56d\", \n\t\t\"tenantCode\": \"4dttetfybz2p0pjpkq79v34olh91qcq7g9l0u7546msbdo50jn\", \n\t\t\"systemId\": \"53850209-57de-43df-9fe9-899d883913d8\", \n\t\t\"systemName\": \"vdvwn55iv9uih7et3du6\", \n\t\t\"executionId\": \"9eb9e5ca-23e3-4879-8d36-3191950cc437\", \n\t\t\"executionType\": \"DETAIL\", \n\t\t\"executionExecutedAt\": \"2020-07-29 08:50:54\", \n\t\t\"executionMonitoringStartAt\": \"2020-07-29 06:58:25\", \n\t\t\"executionMonitoringEndAt\": \"2020-07-29 03:01:43\", \n\t\t\"error\": 4988198006, \n\t\t\"inactive\": 2631492785, \n\t\t\"successful\": 8302023897, \n\t\t\"stopped\": 4995661625, \n\t\t\"unknown\": 3913287678, \n\t\t\"unregistered\": 5491756350\n\t}, \n\t{\n\t\t\"id\": \"dcd9bc2f-9f94-4053-ad13-a562d3771ccd\", \n\t\t\"tenantId\": \"9273b5df-8362-4b6f-9f12-eb3aff5aaaab\", \n\t\t\"tenantCode\": \"qr3ls9kw4bap38c74fq9vpepfgwe8gt2eo4dvfinflxuwf4r52\", \n\t\t\"systemId\": \"20a34c96-8190-4d19-8722-0b9f2a0242b2\", \n\t\t\"systemName\": \"qinynlya60q6mct80yhl\", \n\t\t\"executionId\": \"a0f53a4c-c5f0-415b-a5c5-bd503969d21f\", \n\t\t\"executionType\": \"DETAIL\", \n\t\t\"executionExecutedAt\": \"2020-07-29 12:10:35\", \n\t\t\"executionMonitoringStartAt\": \"2020-07-29 08:50:43\", \n\t\t\"executionMonitoringEndAt\": \"2020-07-29 07:05:02\", \n\t\t\"error\": 8042626848, \n\t\t\"inactive\": 6919959954, \n\t\t\"successful\": 4932094879, \n\t\t\"stopped\": 6366110365, \n\t\t\"unknown\": 3271259959, \n\t\t\"unregistered\": 5441788178\n\t}, \n\t{\n\t\t\"id\": \"4010a7a5-e8b4-434e-9d54-ec8c982cbcdd\", \n\t\t\"tenantId\": \"f3cceddd-0256-4d67-afe4-4b8cd788227f\", \n\t\t\"tenantCode\": \"mmov9xcqwhlc9lus7dt1got5colntf075984ohi4gxdbkqpomg\", \n\t\t\"systemId\": \"32282fab-bc55-4247-bdcc-8dbb92529344\", \n\t\t\"systemName\": \"1tanu7a5r3nu5gwr3f1f\", \n\t\t\"executionId\": \"9b90c989-549c-42d3-baa7-452e967953a7\", \n\t\t\"executionType\": \"DETAIL\", \n\t\t\"executionExecutedAt\": \"2020-07-29 14:51:04\", \n\t\t\"executionMonitoringStartAt\": \"2020-07-28 18:21:23\", \n\t\t\"executionMonitoringEndAt\": \"2020-07-28 19:17:26\", \n\t\t\"error\": 9197556929, \n\t\t\"inactive\": 2889374266, \n\t\t\"successful\": 2278731315, \n\t\t\"stopped\": 9981037782, \n\t\t\"unknown\": 1545944151, \n\t\t\"unregistered\": 2978686816\n\t}, \n\t{\n\t\t\"id\": \"81091903-cdad-44be-b4ea-6850890e3f83\", \n\t\t\"tenantId\": \"d0fe9f75-ecae-4233-ba8a-27fcad14fa24\", \n\t\t\"tenantCode\": \"obbjlsrbv4e1shovpa1985bxslkczd18yn93kym4waizhygl61\", \n\t\t\"systemId\": \"5853ae71-6a4e-474d-8927-2d4f97d99599\", \n\t\t\"systemName\": \"rg1w8vluhrgplr2q3l2m\", \n\t\t\"executionId\": \"7364023d-6892-432c-975b-d586b61947cb\", \n\t\t\"executionType\": \"DETAIL\", \n\t\t\"executionExecutedAt\": \"2020-07-29 04:46:34\", \n\t\t\"executionMonitoringStartAt\": \"2020-07-29 00:07:23\", \n\t\t\"executionMonitoringEndAt\": \"2020-07-29 12:58:20\", \n\t\t\"error\": 6036813826, \n\t\t\"inactive\": 3260914490, \n\t\t\"successful\": 7136697224, \n\t\t\"stopped\": 9674843411, \n\t\t\"unknown\": 2435215110, \n\t\t\"unregistered\": 1233691050\n\t}, \n\t{\n\t\t\"id\": \"45143596-142b-496b-b9c2-3eb01dda4cfa\", \n\t\t\"tenantId\": \"226cc9b8-e729-4773-94e8-8dc47ff06ff9\", \n\t\t\"tenantCode\": \"uv613qc03slwkfzhravs7lml683p0krkzqubv9tq6xqj3hk5ta\", \n\t\t\"systemId\": \"01f4f326-37d3-448b-9fdf-2b616f2b956e\", \n\t\t\"systemName\": \"35nzgwyzh4osrrg309nk\", \n\t\t\"executionId\": \"3f1c6357-a28f-4aca-b76a-7c2cb3155cf9\", \n\t\t\"executionType\": \"DETAIL\", \n\t\t\"executionExecutedAt\": \"2020-07-28 19:50:24\", \n\t\t\"executionMonitoringStartAt\": \"2020-07-28 16:15:01\", \n\t\t\"executionMonitoringEndAt\": \"2020-07-29 07:34:56\", \n\t\t\"error\": 3066933174, \n\t\t\"inactive\": 7630454999, \n\t\t\"successful\": 6063081407, \n\t\t\"stopped\": 3834859415, \n\t\t\"unknown\": 8073579589, \n\t\t\"unregistered\": 9924549880\n\t}, \n\t{\n\t\t\"id\": \"befe6403-cb78-4c4b-964c-f274ab7f3ff9\", \n\t\t\"tenantId\": \"d92a83b9-4500-4548-b53e-426cf4791532\", \n\t\t\"tenantCode\": \"grn8e91sknhx64e2ezm4chvfjfjnjcjv5mqvo80q0ucwibddx9\", \n\t\t\"systemId\": \"9750207d-0613-4997-9784-a154b340741c\", \n\t\t\"systemName\": \"5dy33tf9by11y4gljpub\", \n\t\t\"executionId\": \"c7bba80c-0dce-4885-918d-3254b0e73824\", \n\t\t\"executionType\": \"DETAIL\", \n\t\t\"executionExecutedAt\": \"2020-07-29 09:12:08\", \n\t\t\"executionMonitoringStartAt\": \"2020-07-28 21:57:22\", \n\t\t\"executionMonitoringEndAt\": \"2020-07-29 12:27:18\", \n\t\t\"error\": 3449378888, \n\t\t\"inactive\": 6021408191, \n\t\t\"successful\": 2969873256, \n\t\t\"stopped\": 9811721049, \n\t\t\"unknown\": 4095224790, \n\t\t\"unregistered\": 6878405475\n\t}, \n\t{\n\t\t\"id\": \"a0a70b55-7b33-478d-9b3e-e98231633513\", \n\t\t\"tenantId\": \"3c070aae-f627-4d2b-b4b3-adf5a1b5d2cb\", \n\t\t\"tenantCode\": \"sykx0x2avuchgsz8s7meh40hqp07cp0eradd1a1nc2r4j3ab6n\", \n\t\t\"systemId\": \"882f99b7-c5fd-44d0-b741-42b8c22c4ac6\", \n\t\t\"systemName\": \"spcd0kjipm0ltdjm0hr6\", \n\t\t\"executionId\": \"5f134231-fc56-4704-b7e0-1b9bcc3b13d0\", \n\t\t\"executionType\": \"DETAIL\", \n\t\t\"executionExecutedAt\": \"2020-07-29 08:47:30\", \n\t\t\"executionMonitoringStartAt\": \"2020-07-29 10:23:36\", \n\t\t\"executionMonitoringEndAt\": \"2020-07-28 23:39:31\", \n\t\t\"error\": 9104090146, \n\t\t\"inactive\": 3667050801, \n\t\t\"successful\": 6918060323, \n\t\t\"stopped\": 7230016578, \n\t\t\"unknown\": 3905812223, \n\t\t\"unregistered\": 2419244547\n\t}, \n\t{\n\t\t\"id\": \"68765b5f-6ae4-484a-86af-27a13c68fae4\", \n\t\t\"tenantId\": \"39a457d4-d212-4600-85eb-763850243d88\", \n\t\t\"tenantCode\": \"zwy71uxk6dulkr9vh32kxdh8eyqs7p8rdfslguu1rr2xfh9izb\", \n\t\t\"systemId\": \"1223c897-85dd-4b62-88e6-86a19c8a0586\", \n\t\t\"systemName\": \"y50w582klg6ysxuyl9dt\", \n\t\t\"executionId\": \"7b39070f-612a-4ec1-819b-8d3844816816\", \n\t\t\"executionType\": \"SUMMARY\", \n\t\t\"executionExecutedAt\": \"2020-07-29 00:57:17\", \n\t\t\"executionMonitoringStartAt\": \"2020-07-29 14:26:04\", \n\t\t\"executionMonitoringEndAt\": \"2020-07-28 18:24:18\", \n\t\t\"error\": 1469083729, \n\t\t\"inactive\": 9795886344, \n\t\t\"successful\": 6007449776, \n\t\t\"stopped\": 1908584815, \n\t\t\"unknown\": 2638210357, \n\t\t\"unregistered\": 2968357327\n\t}, \n\t{\n\t\t\"id\": \"b9b5a63a-6efc-45a0-8d43-fa3dd7f2450c\", \n\t\t\"tenantId\": \"aca852ac-1ad9-4b92-b096-86800b2b1e89\", \n\t\t\"tenantCode\": \"ekrks9meu6r0pw1k5sffie1ti6g3c917levvzarqb6l1gfkrzu\", \n\t\t\"systemId\": \"4306492e-4dfe-446e-bcb2-587c56d6b2a2\", \n\t\t\"systemName\": \"ordm4ewfvb1aykvciw0i\", \n\t\t\"executionId\": \"9401d493-bc04-4fd3-83e7-2e561356a352\", \n\t\t\"executionType\": \"SUMMARY\", \n\t\t\"executionExecutedAt\": \"2020-07-29 05:51:35\", \n\t\t\"executionMonitoringStartAt\": \"2020-07-28 20:14:27\", \n\t\t\"executionMonitoringEndAt\": \"2020-07-29 07:18:38\", \n\t\t\"error\": 2147054307, \n\t\t\"inactive\": 1013197003, \n\t\t\"successful\": 8172664561, \n\t\t\"stopped\": 4446955815, \n\t\t\"unknown\": 8088670092, \n\t\t\"unregistered\": 3699627177\n\t}, \n\t{\n\t\t\"id\": \"a2855b6e-ef06-47cd-9270-cec6139df9ed\", \n\t\t\"tenantId\": \"ca9e322a-19ee-4b4e-b650-f7424cd3c0ee\", \n\t\t\"tenantCode\": \"y3qs18w3mi3ws16gvj1akyh9c8sam4q3km1sy1tg3qqzomi39a\", \n\t\t\"systemId\": \"b0e4baec-dadd-434f-953b-d7fee7d21d51\", \n\t\t\"systemName\": \"jfnbfhzc9hquayssovcd\", \n\t\t\"executionId\": \"d2ab7369-048a-4a9f-b7f9-a15abee95a6f\", \n\t\t\"executionType\": \"DETAIL\", \n\t\t\"executionExecutedAt\": \"2020-07-29 05:23:32\", \n\t\t\"executionMonitoringStartAt\": \"2020-07-29 02:04:46\", \n\t\t\"executionMonitoringEndAt\": \"2020-07-29 07:51:05\", \n\t\t\"error\": 4950617769, \n\t\t\"inactive\": 5271179072, \n\t\t\"successful\": 1375159516, \n\t\t\"stopped\": 9332724998, \n\t\t\"unknown\": 1108942632, \n\t\t\"unregistered\": 5325060515\n\t}, \n\t{\n\t\t\"id\": \"2e08b42c-d14b-4258-9243-e4890b092be5\", \n\t\t\"tenantId\": \"bf98ed77-74d2-4d46-be34-568689a1f55a\", \n\t\t\"tenantCode\": \"5uf6u9r4337ytynhnhfpceokf6p3qw99chr9ewoenuubdfo05j\", \n\t\t\"systemId\": \"c901aa72-bb00-45c9-8f55-e36a56ad8ace\", \n\t\t\"systemName\": \"szmul1b0ct67r5ei3j22\", \n\t\t\"executionId\": \"6f123cf9-a801-432b-9f85-925aa7134738\", \n\t\t\"executionType\": \"DETAIL\", \n\t\t\"executionExecutedAt\": \"2020-07-28 18:45:31\", \n\t\t\"executionMonitoringStartAt\": \"2020-07-29 15:31:09\", \n\t\t\"executionMonitoringEndAt\": \"2020-07-28 18:56:23\", \n\t\t\"error\": 1507297358, \n\t\t\"inactive\": 9136572499, \n\t\t\"successful\": 9866362779, \n\t\t\"stopped\": 8844551313, \n\t\t\"unknown\": 8204973391, \n\t\t\"unregistered\": 6395818695\n\t}, \n\t{\n\t\t\"id\": \"db87d777-6d5a-48b3-b22f-719e7d332b6a\", \n\t\t\"tenantId\": \"41561db3-da23-4535-a10c-9b63640a384f\", \n\t\t\"tenantCode\": \"5bi5bq6qceh9jozz7m450h1ifcy94i2uyq8eqp3w5h70voenfu\", \n\t\t\"systemId\": \"3d4b0a07-ba1a-487b-9437-c6978ac02624\", \n\t\t\"systemName\": \"dv8tgm5nw62pap6ylien\", \n\t\t\"executionId\": \"62c9571d-2f14-4b9e-b42d-d5499bc89d34\", \n\t\t\"executionType\": \"DETAIL\", \n\t\t\"executionExecutedAt\": \"2020-07-29 11:53:48\", \n\t\t\"executionMonitoringStartAt\": \"2020-07-29 07:32:37\", \n\t\t\"executionMonitoringEndAt\": \"2020-07-29 08:15:19\", \n\t\t\"error\": 3202648092, \n\t\t\"inactive\": 2593711045, \n\t\t\"successful\": 7505185843, \n\t\t\"stopped\": 7311333465, \n\t\t\"unknown\": 5513156280, \n\t\t\"unregistered\": 2540658813\n\t}, \n\t{\n\t\t\"id\": \"d50008c0-3b9b-4223-b2a5-73a089614169\", \n\t\t\"tenantId\": \"2fe156fa-2630-4478-8970-3846b50c279b\", \n\t\t\"tenantCode\": \"knmf3b36d4nff9pf3qul213z2t9pqov29y7ldf00yczuyrgc0k\", \n\t\t\"systemId\": \"432d6ee1-a9fa-4b3f-bade-bacea938750d\", \n\t\t\"systemName\": \"86safl29sg63w7c7bdz4\", \n\t\t\"executionId\": \"49215212-b9a9-42bc-bf7e-a36a613adf75\", \n\t\t\"executionType\": \"DETAIL\", \n\t\t\"executionExecutedAt\": \"2020-07-29 09:13:00\", \n\t\t\"executionMonitoringStartAt\": \"2020-07-29 10:41:09\", \n\t\t\"executionMonitoringEndAt\": \"2020-07-29 08:56:18\", \n\t\t\"error\": 7307135671, \n\t\t\"inactive\": 1188631893, \n\t\t\"successful\": 2966193362, \n\t\t\"stopped\": 4678998728, \n\t\t\"unknown\": 8597784609, \n\t\t\"unregistered\": 1303945478\n\t}, \n\t{\n\t\t\"id\": \"9dba4882-4f1f-4e0e-a1d7-a3d71cfb0cc1\", \n\t\t\"tenantId\": \"9b808ccb-cd54-4cfb-b0e2-96866db2724f\", \n\t\t\"tenantCode\": \"uhk03ld7u7fa3mczgiyrmtukrkurhy0exjn8u8cax5zghxfo2t\", \n\t\t\"systemId\": \"9e47d0da-381e-42ea-8b5d-078369d2d9ab\", \n\t\t\"systemName\": \"r5pkvxctyu1dpzt5c3mv\", \n\t\t\"executionId\": \"2c050fea-317b-4ddb-b894-999620c31bb5\", \n\t\t\"executionType\": \"DETAIL\", \n\t\t\"executionExecutedAt\": \"2020-07-29 08:24:02\", \n\t\t\"executionMonitoringStartAt\": \"2020-07-28 22:59:42\", \n\t\t\"executionMonitoringEndAt\": \"2020-07-28 22:29:48\", \n\t\t\"error\": 3353899158, \n\t\t\"inactive\": 3998460641, \n\t\t\"successful\": 8350934741, \n\t\t\"stopped\": 6310814699, \n\t\t\"unknown\": 5985596557, \n\t\t\"unregistered\": 5655063459\n\t}, \n\t{\n\t\t\"id\": \"e8eab723-66f3-4e0e-bcd5-ec99ed743722\", \n\t\t\"tenantId\": \"da9e9e24-b538-42a8-8878-1cf8b9aa23a4\", \n\t\t\"tenantCode\": \"fbxstb3nbsa72d01mwmu9i5mo6i76jwolrhqukq7ue2jot00g5\", \n\t\t\"systemId\": \"e6d9c101-35bd-48bc-a2e6-c365cac6355c\", \n\t\t\"systemName\": \"hof7tv93rrh74ticqncq\", \n\t\t\"executionId\": \"2583e395-3ec4-4821-883e-a557d324867b\", \n\t\t\"executionType\": \"DETAIL\", \n\t\t\"executionExecutedAt\": \"2020-07-29 14:17:50\", \n\t\t\"executionMonitoringStartAt\": \"2020-07-29 11:06:13\", \n\t\t\"executionMonitoringEndAt\": \"2020-07-29 14:21:21\", \n\t\t\"error\": 5402656889, \n\t\t\"inactive\": 8807908225, \n\t\t\"successful\": 5862501794, \n\t\t\"stopped\": 7595184973, \n\t\t\"unknown\": 7216016714, \n\t\t\"unregistered\": 6504088799\n\t}, \n\t{\n\t\t\"id\": \"bd91db96-08be-442c-9d53-29ecefe8efa6\", \n\t\t\"tenantId\": \"036e458c-2c14-4c52-a24f-81d3e8ac1bac\", \n\t\t\"tenantCode\": \"0huywzj2go82mydzmitv7opfenb817bauk4gwexmbb4ej2pyry\", \n\t\t\"systemId\": \"fc2212da-42bb-456c-8b3c-cb7878a95530\", \n\t\t\"systemName\": \"euza3tz8fk0ulb0m6vgu\", \n\t\t\"executionId\": \"1dc5dea4-4def-4e83-9e79-91c5059aa891\", \n\t\t\"executionType\": \"DETAIL\", \n\t\t\"executionExecutedAt\": \"2020-07-29 11:44:32\", \n\t\t\"executionMonitoringStartAt\": \"2020-07-29 13:57:26\", \n\t\t\"executionMonitoringEndAt\": \"2020-07-28 17:36:51\", \n\t\t\"error\": 3608848102, \n\t\t\"inactive\": 6055885136, \n\t\t\"successful\": 5062125851, \n\t\t\"stopped\": 2957862159, \n\t\t\"unknown\": 3147604496, \n\t\t\"unregistered\": 7924061209\n\t}, \n\t{\n\t\t\"id\": \"0de36aa6-d64d-4bcf-bb49-2a6df7285185\", \n\t\t\"tenantId\": \"86cf9560-a406-489e-8108-b68c88cd395a\", \n\t\t\"tenantCode\": \"xg8wf3qffrj0yieuyrivleqh6kbtzzu4lvih80uqldw76cen2h\", \n\t\t\"systemId\": \"e5086806-5209-477f-a1d2-4c663d8221c2\", \n\t\t\"systemName\": \"gh7ypz6qlxmbnn9ls5we\", \n\t\t\"executionId\": \"64dc96f1-6d9a-4a28-b96f-c50eb5453840\", \n\t\t\"executionType\": \"DETAIL\", \n\t\t\"executionExecutedAt\": \"2020-07-29 12:23:18\", \n\t\t\"executionMonitoringStartAt\": \"2020-07-29 02:14:47\", \n\t\t\"executionMonitoringEndAt\": \"2020-07-28 23:59:14\", \n\t\t\"error\": 6584290652, \n\t\t\"inactive\": 2076365091, \n\t\t\"successful\": 3586612712, \n\t\t\"stopped\": 4000954160, \n\t\t\"unknown\": 2497079480, \n\t\t\"unregistered\": 2226249489\n\t}, \n\t{\n\t\t\"id\": \"bb44ee6f-48b8-4e01-881d-214cfb8c6d29\", \n\t\t\"tenantId\": \"39a78319-e22e-405e-8b00-543268dd7872\", \n\t\t\"tenantCode\": \"ghtjzx3lj609zmnsmgyt3vx7hu7pi5uiegdpzig7nhzbpioykr\", \n\t\t\"systemId\": \"8c81da5d-8e2e-439d-bb08-1eca7c43764d\", \n\t\t\"systemName\": \"vcfgztyenu256c2q6qhb\", \n\t\t\"executionId\": \"39d28a02-ac93-4e88-9dd8-6f4188b65877\", \n\t\t\"executionType\": \"DETAIL\", \n\t\t\"executionExecutedAt\": \"2020-07-28 22:54:30\", \n\t\t\"executionMonitoringStartAt\": \"2020-07-28 19:35:46\", \n\t\t\"executionMonitoringEndAt\": \"2020-07-28 17:45:59\", \n\t\t\"error\": 4652075655, \n\t\t\"inactive\": 1268299220, \n\t\t\"successful\": 7072592879, \n\t\t\"stopped\": 6795693701, \n\t\t\"unknown\": 5625728597, \n\t\t\"unregistered\": 3163836829\n\t}, \n\t{\n\t\t\"id\": \"741c75b5-7b8b-4109-bcdb-5fc6e24dd800\", \n\t\t\"tenantId\": \"f33b3a6a-7d97-42af-9786-56fc24103a38\", \n\t\t\"tenantCode\": \"d1d6kfcbcndcons6f3f1jjgh1avx6ea3yvw05n5nsnick7cofy\", \n\t\t\"systemId\": \"1d018f73-990e-4df1-b1ba-96d82c71d7a3\", \n\t\t\"systemName\": \"27phbgcfl09q2pr1yqfa\", \n\t\t\"executionId\": \"16272cb8-d035-4890-9c08-53c3b6b58c38\", \n\t\t\"executionType\": \"DETAIL\", \n\t\t\"executionExecutedAt\": \"2020-07-29 00:29:11\", \n\t\t\"executionMonitoringStartAt\": \"2020-07-29 04:18:55\", \n\t\t\"executionMonitoringEndAt\": \"2020-07-29 03:52:32\", \n\t\t\"error\": 6406369944, \n\t\t\"inactive\": 2678613887, \n\t\t\"successful\": 9935494249, \n\t\t\"stopped\": 8742268261, \n\t\t\"unknown\": 2035163429, \n\t\t\"unregistered\": 4419307544\n\t}, \n\t{\n\t\t\"id\": \"e3bc2695-c10d-4ce4-9fac-cc3e49004e6d\", \n\t\t\"tenantId\": \"b0dde136-dfb0-4713-afc1-e3f6ef3f1f2f\", \n\t\t\"tenantCode\": \"nvbbgqwwxgcmdh7scl2d0wwypv8e1sv5xowsbmmzd5ay796kzt\", \n\t\t\"systemId\": \"575aff4b-cd4c-481d-92f6-a8c2a2811640\", \n\t\t\"systemName\": \"ur62ksxzqu8k6yg03axx\", \n\t\t\"executionId\": \"ba72b14a-f5c3-4e9d-b4c9-09b0603378cc\", \n\t\t\"executionType\": \"SUMMARY\", \n\t\t\"executionExecutedAt\": \"2020-07-29 06:26:59\", \n\t\t\"executionMonitoringStartAt\": \"2020-07-29 03:46:11\", \n\t\t\"executionMonitoringEndAt\": \"2020-07-29 14:06:20\", \n\t\t\"error\": 1333335703, \n\t\t\"inactive\": 6239711288, \n\t\t\"successful\": 7161821818, \n\t\t\"stopped\": 2118924417, \n\t\t\"unknown\": 3814788328, \n\t\t\"unregistered\": 7549055294\n\t}\n]",
					"options": {
						"raw": {
							"language": "json"
						}
					}
				},
				"url": {
					"raw": "{{URL}}/bplus-it-sappi/channels-overview",
					"host": [
						"{{URL}}"
					],
					"path": [
						"bplus-it-sappi",
						"channels-overview"
					]
				}
			},
			"response": []
        },
        {
			"name": "REST - bplus-it-sappi/channels-overview/paginate",
			"protocolProfileBehavior": {
				"disableBodyPruning": true
			},
			"request": {
				"method": "GET",
				"header": [
					{
						"key": "Content-Type",
						"name": "Content-Type",
						"type": "text",
						"value": "application/json"
					}
				],
				"body": {
					"mode": "raw",
					"raw": "{\n\t\"query\":\n\t[\n\t\t{\n\t\t\t\"command\": \"OFFSET\",\n\t\t\t\"value\": 0\n\t\t},\n\t\t{\n\t\t\t\"command\": \"LIMIT\",\n\t\t\t\"value\": 10\n\t\t}\n\t]\n}",
					"options": {
						"raw": {
							"language": "json"
						}
					}
				},
				"url": {
					"raw": "{{URL}}/bplus-it-sappi/channels-overview/paginate",
					"host": [
						"{{URL}}"
					],
					"path": [
						"bplus-it-sappi",
                        "channels-overview",
                        "paginate"
					]
				}
			},
			"response": []
        },
        {
			"name": "REST - bplus-it-sappi/channels-overview",
			"protocolProfileBehavior": {
				"disableBodyPruning": true
			},
			"request": {
				"method": "GET",
				"header": [
					{
						"key": "Content-Type",
						"name": "Content-Type",
						"type": "text",
						"value": "application/json"
					}
				],
				"body": {
					"mode": "raw",
					"raw": "{\n\t\"query\":\n\t[\n\t\t{\n\t\t\t\"command\": \"WHERE\",\n\t\t\t\"column\": \"id\",\n\t\t\t\"operator\": \"EQUALS\",\n\t\t\t\"value\": \"e483c0ba-8758-493b-8fc2-c4649fcb0f2a\"\n\t\t}\n\t]\n}",
					"options": {
						"raw": {
							"language": "json"
						}
					}
				},
				"url": {
					"raw": "{{URL}}/bplus-it-sappi/channels-overview",
					"host": [
						"{{URL}}"
					],
					"path": [
						"bplus-it-sappi",
						"channels-overview"
					]
				}
			},
			"response": []
        },
        {
			"name": "REST - bplus-it-sappi/channel-overview",
			"protocolProfileBehavior": {
				"disableBodyPruning": true
			},
			"request": {
				"method": "GET",
				"header": [
					{
						"key": "Content-Type",
						"name": "Content-Type",
						"type": "text",
						"value": "application/json"
					}
				],
				"body": {
					"mode": "raw",
					"raw": "{\n\t\"query\":\n\t[\n\t\t{\n\t\t\t\"command\": \"WHERE\",\n\t\t\t\"column\": \"id\",\n\t\t\t\"operator\": \"EQUALS\",\n\t\t\t\"value\": \"e483c0ba-8758-493b-8fc2-c4649fcb0f2a\"\n\t\t}\n\t]\n}",
					"options": {
						"raw": {
							"language": "json"
						}
					}
				},
				"url": {
					"raw": "{{URL}}/bplus-it-sappi/channel-overview",
					"host": [
						"{{URL}}"
					],
					"path": [
						"bplus-it-sappi",
						"channel-overview"
					]
				}
			},
			"response": []
        },
        {
			"name": "REST - bplus-it-sappi/channel-overview/{id}",
			"protocolProfileBehavior": {
				"disableBodyPruning": true
			},
			"request": {
				"method": "GET",
				"header": [
					{
						"key": "Content-Type",
						"name": "Content-Type",
						"type": "text",
						"value": "application/json"
					}
				],
				"body": {
					"mode": "raw",
					"raw": "",
					"options": {
						"raw": {
							"language": "json"
						}
					}
				},
				"url": {
					"raw": "{{URL}}/bplus-it-sappi/channel-overview/e483c0ba-8758-493b-8fc2-c4649fcb0f2a",
					"host": [
						"{{URL}}"
					],
					"path": [
						"bplus-it-sappi",
						"channel-overview",
						"e483c0ba-8758-493b-8fc2-c4649fcb0f2a"
					]
				}
			},
			"response": []
        },
        {
			"name": "REST - bplus-it-sappi/channel-overview",
			"request": {
				"method": "PUT",
				"header": [
					{
						"key": "Content-Type",
						"name": "Content-Type",
						"type": "text",
						"value": "application/json"
					}
				],
				"body": {
					"mode": "raw",
					"raw"   : "{\n\t\"id\": \"e483c0ba-8758-493b-8fc2-c4649fcb0f2a\", \n\t\"tenantId\": \"1c56f03a-c62d-4233-9d01-1384da5dea11\", \n\t\"tenantCode\": \"e6xuftkk2bti96u006vcqtnzscd47wv2kw23xfx8sumydex4dj\", \n\t\"systemId\": \"f51dee00-203a-4efc-b6ce-336414c2943a\", \n\t\"systemName\": \"6gopj170h31jh4n8wg50\", \n\t\"executionId\": \"db6388d3-eb59-4ce7-a270-704fdde0eaea\", \n\t\"executionType\": \"SUMMARY\", \n\t\"executionExecutedAt\": \"2020-07-29 00:06:17\", \n\t\"executionMonitoringStartAt\": \"2020-07-29 01:16:48\", \n\t\"executionMonitoringEndAt\": \"2020-07-29 00:13:22\", \n\t\"error\": 7949580009, \n\t\"inactive\": 3136459701, \n\t\"successful\": 1501989894, \n\t\"stopped\": 6214573367, \n\t\"unknown\": 7738494554, \n\t\"unregistered\": 7824857142\n}",
					"options": {
						"raw": {
							"language": "json"
						}
					}
				},
				"url": {
					"raw": "{{URL}}/bplus-it-sappi/channel-overview",
					"host": [
						"{{URL}}"
					],
					"path": [
						"bplus-it-sappi",
						"channel-overview"
					]
				}
			},
			"response": []
        },
        {
			"name": "REST - bplus-it-sappi/channel-overview/{id}",
			"request": {
				"method": "DELETE",
				"header": [
					{
						"key": "Content-Type",
						"name": "Content-Type",
						"type": "text",
						"value": "application/json"
					}
				],
				"body": {
					"mode": "raw",
					"raw": "",
					"options": {
						"raw": {
							"language": "json"
						}
					}
				},
				"url": {
					"raw": "{{URL}}/bplus-it-sappi/channel-overview/e483c0ba-8758-493b-8fc2-c4649fcb0f2a",
					"host": [
						"{{URL}}"
					],
					"path": [
						"bplus-it-sappi",
						"channel-overview",
						"e483c0ba-8758-493b-8fc2-c4649fcb0f2a"
					]
				}
			},
			"response": []
		},
        {
			"name": "REST - bplus-it-sappi/channels-overview",
			"request": {
				"method": "DELETE",
				"header": [
					{
						"key": "Content-Type",
						"name": "Content-Type",
						"type": "text",
						"value": "application/json"
					}
				],
				"body": {
					"mode": "raw",
					"raw": "{\n\t\"query\":\n\t[\n\t\t{\n\t\t\t\"command\": \"WHERE\",\n\t\t\t\"column\": \"id\",\n\t\t\t\"operator\": \"CONTAINS\",\n\t\t\t\"value\": \"%%\"\n\t\t}\n\t]\n}",
					"options": {
						"raw": {
							"language": "json"
						}
					}
				},
				"url": {
					"raw": "{{URL}}/bplus-it-sappi/channels-overview",
					"host": [
						"{{URL}}"
					],
					"path": [
						"bplus-it-sappi",
						"channels-overview"
					]
				}
			},
			"response": []
		}
    ],
    "variable": [
		{
			"id": "99e6bda1-ad16-4eb6-aa6b-f738f2c11b65",
			"key": "URL",
			"value": "http://localhost:8080",
			"type": "string"
		}
	]
}