{
    "info": {
		"_postman_id"   : "f68ac95f-1262-4c70-8370-5427b472e5d1",
		"name"          : "@hades - iam/account",
		"schema"        : "https://schema.getpostman.com/json/collection/v2.1.0/collection.json"
    },
    "item": [
        {
			"name": "GraphQL - iamCreateAccount",
			"request": {
				"method": "POST",
				"header": [],
				"body": {
					"mode": "graphql",
					"graphql": {
						"query": "mutation ($payload:IamCreateAccountInput!)\n{\n\tiamCreateAccount (payload:$payload)\n\t{\n\t\tid\n\t\ttype\n\t\temail\n\t\tisActive\n\t\tclientId\n\t\tdApplicationCodes\n\t\tdPermissions\n\t\tdTenants\n\t\tdata\n\t\tcreatedAt\n\t\tupdatedAt\n\t}\n}",
						"variables": "{\n\t\"payload\":\n\t{\n\t\t\"id\": \"7587d893-0ac2-4ef2-83e1-c35b2f3fd213\", \n\t\t\"type\": \"USER\", \n\t\t\"email\": \"8px6inbv0ib563lh7cmfhesg90xhjmb4qbg1ynf07hm077wqs9rs52nwkip2i211b3y9z8lnowgu4435uv0cyg8a9qfpm5tl2kzafahdhcfa9kcxrhdvf8cc\", \n\t\t\"isActive\": true, \n\t\t\"clientId\": \"0bec85f7-356c-4b0c-9343-84f6b60960f5\", \n\t\t\"dApplicationCodes\": { \"foo\" : \"bar\" }, \n\t\t\"dPermissions\": { \"foo\" : \"bar\" }, \n\t\t\"dTenants\": { \"foo\" : \"bar\" }, \n\t\t\"data\": { \"foo\" : \"bar\" }, \n\t\t\"roleIds\": [], \n\t\t\"tenantIds\": []\n\t}\n}"
					}
				},
				"url": {
					"raw": "{{URL}}/graphql",
					"host": [
						"{{URL}}"
					],
					"path": [
						"graphql"
					]
				}
			},
			"response": []
        },
        {
			"name": "GraphQL - iamCreateAccounts",
			"request": {
				"method": "POST",
				"header": [],
				"body": {
					"mode": "graphql",
					"graphql": {
						"query": "mutation ($payload:[IamCreateAccountInput]!)\n{\n\tiamCreateAccounts (payload:$payload)\n}",
						"variables": "{\n\t\"payload\":\n\t[\n\t\t{\n\t\t\t\"id\": \"9902bfab-0849-4dcd-a936-a80a141cd1b3\", \n\t\t\t\"type\": \"SERVICE\", \n\t\t\t\"email\": \"89h6hwryhim30z1n2n52rkhqyhkbb966qb70t2z2fhlp9vp0fugltp2252tbdljgikthc0vdlzdyf3yzdmccph92tl0mr2qtzaxi28bnb3n2szshin7g4ulc\", \n\t\t\t\"isActive\": false, \n\t\t\t\"clientId\": \"023b8ebb-1efc-4037-93a8-18d367c5b5b3\", \n\t\t\t\"dApplicationCodes\": { \"foo\" : \"bar\" }, \n\t\t\t\"dPermissions\": { \"foo\" : \"bar\" }, \n\t\t\t\"dTenants\": { \"foo\" : \"bar\" }, \n\t\t\t\"data\": { \"foo\" : \"bar\" }, \n\t\t\t\"roleIds\": [], \n\t\t\t\"tenantIds\": []\n\t\t},\n\t\t{\n\t\t\t\"id\": \"b44641fb-b99d-41a5-9d8d-c1ea3063d2c0\", \n\t\t\t\"type\": \"SERVICE\", \n\t\t\t\"email\": \"i5ictn2i253dqzclo1tfys0p2droj76pawuehvf6ibtc5e3aspvr3zb4jsftsocq5t7tradvssw9c3s531wxw3bqskb67m9tpd0zs111s5kplwumhmr4ckbm\", \n\t\t\t\"isActive\": false, \n\t\t\t\"clientId\": \"7a9657c7-478d-4282-b2f7-7906ce4e8c5e\", \n\t\t\t\"dApplicationCodes\": { \"foo\" : \"bar\" }, \n\t\t\t\"dPermissions\": { \"foo\" : \"bar\" }, \n\t\t\t\"dTenants\": { \"foo\" : \"bar\" }, \n\t\t\t\"data\": { \"foo\" : \"bar\" }, \n\t\t\t\"roleIds\": [], \n\t\t\t\"tenantIds\": []\n\t\t},\n\t\t{\n\t\t\t\"id\": \"695fd610-8e3f-424f-9ce2-e71656b12164\", \n\t\t\t\"type\": \"USER\", \n\t\t\t\"email\": \"6puw75gla8pjbem0gvy6ilwsdbb9tqa08n7r7zgz8xxonkzluokdyr1snuggh65x75uym8a7v2wlsacroqns12z56dft12u8slxrg5kvktxfj6h2r5mrbato\", \n\t\t\t\"isActive\": true, \n\t\t\t\"clientId\": \"592003c0-8ebf-42fe-95f8-be58bce451d3\", \n\t\t\t\"dApplicationCodes\": { \"foo\" : \"bar\" }, \n\t\t\t\"dPermissions\": { \"foo\" : \"bar\" }, \n\t\t\t\"dTenants\": { \"foo\" : \"bar\" }, \n\t\t\t\"data\": { \"foo\" : \"bar\" }, \n\t\t\t\"roleIds\": [], \n\t\t\t\"tenantIds\": []\n\t\t},\n\t\t{\n\t\t\t\"id\": \"b5868ca6-2acb-4a61-ba0f-996858297990\", \n\t\t\t\"type\": \"USER\", \n\t\t\t\"email\": \"3ae5oh7lf8iyovfquma6pl5qyru37t0mgsirdxakvyo8em1zfgpnw4otrhvl9ci3ynimxh5mewtol37f2ro32miq76ytaecdra5uqnmzk7sg423x3ajip3gf\", \n\t\t\t\"isActive\": true, \n\t\t\t\"clientId\": \"8c46a868-82d7-4965-bb6e-dbbba2ac7ea0\", \n\t\t\t\"dApplicationCodes\": { \"foo\" : \"bar\" }, \n\t\t\t\"dPermissions\": { \"foo\" : \"bar\" }, \n\t\t\t\"dTenants\": { \"foo\" : \"bar\" }, \n\t\t\t\"data\": { \"foo\" : \"bar\" }, \n\t\t\t\"roleIds\": [], \n\t\t\t\"tenantIds\": []\n\t\t},\n\t\t{\n\t\t\t\"id\": \"d67d95b4-8292-474b-a4f0-fa35b5533ee5\", \n\t\t\t\"type\": \"USER\", \n\t\t\t\"email\": \"s1ffapw5ta9qvhskvwnru849m1016b8yhy01j96al5kqt2l1nbg316ehm5ld2638ru9jgsoaj2hk66w9am34124glc69l0dphs2v20g9etgi127mkuyanqan\", \n\t\t\t\"isActive\": false, \n\t\t\t\"clientId\": \"3a3371ab-d4f5-4620-9e39-66d9a69d1f89\", \n\t\t\t\"dApplicationCodes\": { \"foo\" : \"bar\" }, \n\t\t\t\"dPermissions\": { \"foo\" : \"bar\" }, \n\t\t\t\"dTenants\": { \"foo\" : \"bar\" }, \n\t\t\t\"data\": { \"foo\" : \"bar\" }, \n\t\t\t\"roleIds\": [], \n\t\t\t\"tenantIds\": []\n\t\t},\n\t\t{\n\t\t\t\"id\": \"70ca0a8f-b794-4e39-82aa-44dfe40f9278\", \n\t\t\t\"type\": \"USER\", \n\t\t\t\"email\": \"bwu8r9u043k7m4liu1xtnb0w2j7fcx6t1eip6ddcp7y8zh9plxarwrcbp0egq0lo4m08xln6t1h97bn86ntmqjps31ybda8oix9viltcfmxfvseectni88wu\", \n\t\t\t\"isActive\": true, \n\t\t\t\"clientId\": \"63f0d34a-2c75-4ddb-865f-8005052a0544\", \n\t\t\t\"dApplicationCodes\": { \"foo\" : \"bar\" }, \n\t\t\t\"dPermissions\": { \"foo\" : \"bar\" }, \n\t\t\t\"dTenants\": { \"foo\" : \"bar\" }, \n\t\t\t\"data\": { \"foo\" : \"bar\" }, \n\t\t\t\"roleIds\": [], \n\t\t\t\"tenantIds\": []\n\t\t},\n\t\t{\n\t\t\t\"id\": \"8be26034-6cf4-46eb-8734-34e44d12ff9c\", \n\t\t\t\"type\": \"USER\", \n\t\t\t\"email\": \"9vdqq755uzw2pbqklt7eqabo6c132ovz96e1fervx05hpdwqcvsl61uoik7ncg7f14jj353oflj0gpoh4wmvorphogipkr396cg3n5765o1mcj0emt7ojmf2\", \n\t\t\t\"isActive\": true, \n\t\t\t\"clientId\": \"430f33b9-37a6-454b-accc-38dc7b015801\", \n\t\t\t\"dApplicationCodes\": { \"foo\" : \"bar\" }, \n\t\t\t\"dPermissions\": { \"foo\" : \"bar\" }, \n\t\t\t\"dTenants\": { \"foo\" : \"bar\" }, \n\t\t\t\"data\": { \"foo\" : \"bar\" }, \n\t\t\t\"roleIds\": [], \n\t\t\t\"tenantIds\": []\n\t\t},\n\t\t{\n\t\t\t\"id\": \"4cf3cc6e-9f82-485b-91db-0e3a9fc42943\", \n\t\t\t\"type\": \"USER\", \n\t\t\t\"email\": \"nfeuvd1erul4eccjvo10k9seo2w96zm5ozn1w499v7wr4lfmwqd55dn3vnm8ft90b93h8nk8i5htmi9i4z2e20zmxc2puzn2k0n3bbe81tebdrxoy3ipebdh\", \n\t\t\t\"isActive\": true, \n\t\t\t\"clientId\": \"79081ce1-277b-4964-948a-8a4563e88370\", \n\t\t\t\"dApplicationCodes\": { \"foo\" : \"bar\" }, \n\t\t\t\"dPermissions\": { \"foo\" : \"bar\" }, \n\t\t\t\"dTenants\": { \"foo\" : \"bar\" }, \n\t\t\t\"data\": { \"foo\" : \"bar\" }, \n\t\t\t\"roleIds\": [], \n\t\t\t\"tenantIds\": []\n\t\t},\n\t\t{\n\t\t\t\"id\": \"7ccb30aa-5d5a-4381-a8b8-acc3941f6268\", \n\t\t\t\"type\": \"SERVICE\", \n\t\t\t\"email\": \"klhxgr0m71j86kf8wms96cloqydidzxidh2x6o2cy1298umh3ryxjyk5artss9v5ifusbe004jodi0egxtpdo7wt4f4kecwaw8h6t7wr7mteaqpcsw0zevsp\", \n\t\t\t\"isActive\": false, \n\t\t\t\"clientId\": \"97a2fccc-b4c2-4f3c-bf92-5bac0204015b\", \n\t\t\t\"dApplicationCodes\": { \"foo\" : \"bar\" }, \n\t\t\t\"dPermissions\": { \"foo\" : \"bar\" }, \n\t\t\t\"dTenants\": { \"foo\" : \"bar\" }, \n\t\t\t\"data\": { \"foo\" : \"bar\" }, \n\t\t\t\"roleIds\": [], \n\t\t\t\"tenantIds\": []\n\t\t},\n\t\t{\n\t\t\t\"id\": \"842b7469-151f-439c-84e1-8d1d2bdad8d8\", \n\t\t\t\"type\": \"SERVICE\", \n\t\t\t\"email\": \"gphtftpw8aunw3uv1ypxfa5r8sechk5kib2ans2erkahf6tjpytbxpdgl7e378wxinzsfxw7nk71vk54ppa6vzicbvchchgs27u56gj0irt58i8z9mi7gc0b\", \n\t\t\t\"isActive\": true, \n\t\t\t\"clientId\": \"b510f0ad-d65a-45b6-9209-0e24598b84e1\", \n\t\t\t\"dApplicationCodes\": { \"foo\" : \"bar\" }, \n\t\t\t\"dPermissions\": { \"foo\" : \"bar\" }, \n\t\t\t\"dTenants\": { \"foo\" : \"bar\" }, \n\t\t\t\"data\": { \"foo\" : \"bar\" }, \n\t\t\t\"roleIds\": [], \n\t\t\t\"tenantIds\": []\n\t\t},\n\t\t{\n\t\t\t\"id\": \"e1069faf-bb79-407b-a340-755bfaf9a009\", \n\t\t\t\"type\": \"USER\", \n\t\t\t\"email\": \"7y5t8aq19q3zk8zqc0d99vojoaqj9f8dpfverke8k6vu4l5t9tvwmvc6h2ey0u0ibmy9lc3n7ksdtb4xct642atndis2wwu026fry94ijzflmiq5mxk0r9cd\", \n\t\t\t\"isActive\": true, \n\t\t\t\"clientId\": \"443442ca-2df0-452e-8b00-c9e0f680eb7c\", \n\t\t\t\"dApplicationCodes\": { \"foo\" : \"bar\" }, \n\t\t\t\"dPermissions\": { \"foo\" : \"bar\" }, \n\t\t\t\"dTenants\": { \"foo\" : \"bar\" }, \n\t\t\t\"data\": { \"foo\" : \"bar\" }, \n\t\t\t\"roleIds\": [], \n\t\t\t\"tenantIds\": []\n\t\t},\n\t\t{\n\t\t\t\"id\": \"2cd876a4-0b57-4f5d-85bb-3f8ef809e5f4\", \n\t\t\t\"type\": \"SERVICE\", \n\t\t\t\"email\": \"17dsdgibwod62g6lllrma6s61rt2bk7y9x6szay1medw18a69hfe1vh6bncilazz6jsgwyvodva5i3hvgpkqtmql38lg9lgsdqvliw0ffhv4zea8ijqtdvf4\", \n\t\t\t\"isActive\": false, \n\t\t\t\"clientId\": \"afb86bcb-d230-4114-b6ee-5c95a1b55956\", \n\t\t\t\"dApplicationCodes\": { \"foo\" : \"bar\" }, \n\t\t\t\"dPermissions\": { \"foo\" : \"bar\" }, \n\t\t\t\"dTenants\": { \"foo\" : \"bar\" }, \n\t\t\t\"data\": { \"foo\" : \"bar\" }, \n\t\t\t\"roleIds\": [], \n\t\t\t\"tenantIds\": []\n\t\t},\n\t\t{\n\t\t\t\"id\": \"39ee1153-0bca-4e43-aa76-c4d08ab30dd7\", \n\t\t\t\"type\": \"USER\", \n\t\t\t\"email\": \"db2b8vseryngtbi98l2svf5vu1lg7lqs7a1n7nyatfih5ri93xi21o8eko9oigqjg4xgyz67pbi0qbdrvh4fvsk8fyyc627z5fxaaqhawlzz0004h8u7p7v3\", \n\t\t\t\"isActive\": true, \n\t\t\t\"clientId\": \"47dcefae-e3ad-463d-8b1e-a2d7365b5fe2\", \n\t\t\t\"dApplicationCodes\": { \"foo\" : \"bar\" }, \n\t\t\t\"dPermissions\": { \"foo\" : \"bar\" }, \n\t\t\t\"dTenants\": { \"foo\" : \"bar\" }, \n\t\t\t\"data\": { \"foo\" : \"bar\" }, \n\t\t\t\"roleIds\": [], \n\t\t\t\"tenantIds\": []\n\t\t},\n\t\t{\n\t\t\t\"id\": \"1e22ab86-3da2-40e8-9494-3f4ea8e78aa1\", \n\t\t\t\"type\": \"SERVICE\", \n\t\t\t\"email\": \"dtz965qv3zsz3x0fwiitvaa6j5zxqukzcp3z32aaky7rcj815wwhpv2u23gtn55dmnqato9gkanllcnsol4441f43zkiaieyjahocau5y9bcbk9jts03zlga\", \n\t\t\t\"isActive\": false, \n\t\t\t\"clientId\": \"b258b1f9-8460-4e96-a8ab-bce458f23214\", \n\t\t\t\"dApplicationCodes\": { \"foo\" : \"bar\" }, \n\t\t\t\"dPermissions\": { \"foo\" : \"bar\" }, \n\t\t\t\"dTenants\": { \"foo\" : \"bar\" }, \n\t\t\t\"data\": { \"foo\" : \"bar\" }, \n\t\t\t\"roleIds\": [], \n\t\t\t\"tenantIds\": []\n\t\t},\n\t\t{\n\t\t\t\"id\": \"1b6504f8-cefa-4ed5-aaed-bf25fe2c2cd2\", \n\t\t\t\"type\": \"USER\", \n\t\t\t\"email\": \"1n279wv34xzifgngc2xq7ddd7exlerrvmky1dkfx91nn00cw0qceg5m1m59f2hzd9mpx9c8603mk3p06ohjggv26o2q19i0gisvdemf4t5r9wfuj7352lcx6\", \n\t\t\t\"isActive\": true, \n\t\t\t\"clientId\": \"96845d71-165a-49fa-8bd0-7fdd7a668e24\", \n\t\t\t\"dApplicationCodes\": { \"foo\" : \"bar\" }, \n\t\t\t\"dPermissions\": { \"foo\" : \"bar\" }, \n\t\t\t\"dTenants\": { \"foo\" : \"bar\" }, \n\t\t\t\"data\": { \"foo\" : \"bar\" }, \n\t\t\t\"roleIds\": [], \n\t\t\t\"tenantIds\": []\n\t\t},\n\t\t{\n\t\t\t\"id\": \"812f9b5a-301c-4d9a-945a-aecb6fba607f\", \n\t\t\t\"type\": \"USER\", \n\t\t\t\"email\": \"wpgt8br569ifnr7zbj83rqhp7pxzwfxyvtjc1supwj448l5p38pwgtjldg3pd86744z42rbqlj052yy9sdw0hvhk6drs0n8u31s3kdhwa6555xf64lcswugy\", \n\t\t\t\"isActive\": false, \n\t\t\t\"clientId\": \"da390732-8db3-4959-a8f5-2de17586aec4\", \n\t\t\t\"dApplicationCodes\": { \"foo\" : \"bar\" }, \n\t\t\t\"dPermissions\": { \"foo\" : \"bar\" }, \n\t\t\t\"dTenants\": { \"foo\" : \"bar\" }, \n\t\t\t\"data\": { \"foo\" : \"bar\" }, \n\t\t\t\"roleIds\": [], \n\t\t\t\"tenantIds\": []\n\t\t},\n\t\t{\n\t\t\t\"id\": \"f942a3c9-f923-4e66-b539-4f64d96dcd6a\", \n\t\t\t\"type\": \"USER\", \n\t\t\t\"email\": \"punzy2m6b3el5ac7xjh795fhs75q3x0jayzkrpytylf523y9nafwc97gu1y0cfbewg4g0i45z65bjobmlqopr0sm8q4n51qh49otytbosmkslbouohy2xrsd\", \n\t\t\t\"isActive\": true, \n\t\t\t\"clientId\": \"2eb5e168-769a-49fc-973f-bdafa51dbfdf\", \n\t\t\t\"dApplicationCodes\": { \"foo\" : \"bar\" }, \n\t\t\t\"dPermissions\": { \"foo\" : \"bar\" }, \n\t\t\t\"dTenants\": { \"foo\" : \"bar\" }, \n\t\t\t\"data\": { \"foo\" : \"bar\" }, \n\t\t\t\"roleIds\": [], \n\t\t\t\"tenantIds\": []\n\t\t},\n\t\t{\n\t\t\t\"id\": \"83233484-72d5-4314-824d-d8f43b64ec80\", \n\t\t\t\"type\": \"SERVICE\", \n\t\t\t\"email\": \"k6kafx7nxid46t52p96x8p0k7g9cef243b49do2zl4sqpsx705tazrng3nd4d1c4sqpz6f3cvrk8hl27dpbha7xhxwx4nfjjz0crkeksor22gawk9uo49d7j\", \n\t\t\t\"isActive\": false, \n\t\t\t\"clientId\": \"5f99320c-8fc3-4d2d-b921-8e878f58c09e\", \n\t\t\t\"dApplicationCodes\": { \"foo\" : \"bar\" }, \n\t\t\t\"dPermissions\": { \"foo\" : \"bar\" }, \n\t\t\t\"dTenants\": { \"foo\" : \"bar\" }, \n\t\t\t\"data\": { \"foo\" : \"bar\" }, \n\t\t\t\"roleIds\": [], \n\t\t\t\"tenantIds\": []\n\t\t},\n\t\t{\n\t\t\t\"id\": \"45feabd9-0457-4699-bbfd-194c2174cc87\", \n\t\t\t\"type\": \"USER\", \n\t\t\t\"email\": \"jbg96uvr3b1awqe1xht3smaby7bi2wubelqs911w5up4a84j144hedscrnz46ch7htju4n8e3mevc7gtoniauzja2moicwp2ph8mish3i73ypln6ug3x0wdn\", \n\t\t\t\"isActive\": false, \n\t\t\t\"clientId\": \"559287be-c43c-4479-ba9b-8b339833f513\", \n\t\t\t\"dApplicationCodes\": { \"foo\" : \"bar\" }, \n\t\t\t\"dPermissions\": { \"foo\" : \"bar\" }, \n\t\t\t\"dTenants\": { \"foo\" : \"bar\" }, \n\t\t\t\"data\": { \"foo\" : \"bar\" }, \n\t\t\t\"roleIds\": [], \n\t\t\t\"tenantIds\": []\n\t\t},\n\t\t{\n\t\t\t\"id\": \"629c3f2a-5842-4ceb-b788-66deafcdad4a\", \n\t\t\t\"type\": \"SERVICE\", \n\t\t\t\"email\": \"vmxsic940w6eh9zd1feebi77khcq4wdz8ooih42t0d3zufckau2xq8wdpexnjk7ldu97r54cbogekf7365x40dwq0igr4og0fosaadk2dm6kyoytbd185qqb\", \n\t\t\t\"isActive\": true, \n\t\t\t\"clientId\": \"f8e0b437-ab7b-416a-bef5-59f88eb1d88e\", \n\t\t\t\"dApplicationCodes\": { \"foo\" : \"bar\" }, \n\t\t\t\"dPermissions\": { \"foo\" : \"bar\" }, \n\t\t\t\"dTenants\": { \"foo\" : \"bar\" }, \n\t\t\t\"data\": { \"foo\" : \"bar\" }, \n\t\t\t\"roleIds\": [], \n\t\t\t\"tenantIds\": []\n\t\t}\n\t]\n}"
					}
				},
				"url": {
					"raw": "{{URL}}/graphql",
					"host": [
						"{{URL}}"
					],
					"path": [
						"graphql"
					]
				}
			},
			"response": []
        },
        {
			"name": "GraphQL - iamPaginateAccounts",
			"request": {
				"method": "POST",
				"header": [],
				"body": {
					"mode": "graphql",
					"graphql": {
						"query": "query ($query:QueryStatement $constraint:QueryStatement)\n{\n\tiamPaginateAccounts (query:$query constraint:$constraint)\n\t{\n\t\ttotal\n\t\tcount\n\t\trows\n\t}\n}",
						"variables": "{\n\t\"query\":\n\t{\n\t\t\"offset\": 0,\n\t\t\"limit\": 10\n\t}\n}"
					}
				},
				"url": {
					"raw": "{{URL}}/graphql",
					"host": [
						"{{URL}}"
					],
					"path": [
						"graphql"
					]
				}
			},
			"response": []
        },
        {
			"name": "GraphQL - iamGetAccounts",
			"request": {
				"method": "POST",
				"header": [],
				"body": {
					"mode": "graphql",
					"graphql": {
						"query": "query ($query:QueryStatement)\n{\n\tiamGetAccounts (query: $query)\n\t{\n\t\tid\n\t\ttype\n\t\temail\n\t\tisActive\n\t\tclientId\n\t\tdApplicationCodes\n\t\tdPermissions\n\t\tdTenants\n\t\tdata\n\t\tcreatedAt\n\t\tupdatedAt\n\t}\n}",
						"variables": "{\n\t\"query\":\n\t{\n\t\t\"where\":\n\t\t{ \n\t\t\t\"id\": \"7587d893-0ac2-4ef2-83e1-c35b2f3fd213\"\n\t\t}\n\t}\n}"
					}
				},
				"url": {
					"raw": "{{URL}}/graphql",
					"host": [
						"{{URL}}"
					],
					"path": [
						"graphql"
					]
				}
			},
			"response": []
        },
        {
			"name": "GraphQL - iamFindAccount",
			"request": {
				"method": "POST",
				"header": [],
				"body": {
					"mode": "graphql",
					"graphql": {
						"query": "query ($query:QueryStatement)\n{\n\tiamFindAccount (query: $query)\n\t{\n\t\tid\n\t\ttype\n\t\temail\n\t\tisActive\n\t\tclientId\n\t\tdApplicationCodes\n\t\tdPermissions\n\t\tdTenants\n\t\tdata\n\t\tcreatedAt\n\t\tupdatedAt\n\t}\n}",
						"variables": "{\n\t\"query\":\n\t{\n\t\t\"where\":\n\t\t{\n\t\t\t\"id\": \"7587d893-0ac2-4ef2-83e1-c35b2f3fd213\"\n\t\t}\n\t}\n}"
					}
				},
				"url": {
					"raw": "{{URL}}/graphql",
					"host": [
						"{{URL}}"
					],
					"path": [
						"graphql"
					]
				}
			},
			"response": []
        },
        {
			"name": "GraphQL - iamFindAccountById",
			"request": {
				"method": "POST",
				"header": [],
				"body": {
					"mode": "graphql",
					"graphql": {
						"query": "query ($id:ID)\n{\n\tiamFindAccountById (id:$id)\n\t{\n\t\tid\n\t\ttype\n\t\temail\n\t\tisActive\n\t\tclientId\n\t\tdApplicationCodes\n\t\tdPermissions\n\t\tdTenants\n\t\tdata\n\t\tcreatedAt\n\t\tupdatedAt\n\t}\n}",
						"variables": "{\n\t\"id\": \"7587d893-0ac2-4ef2-83e1-c35b2f3fd213\"\n}"
					}
				},
				"url": {
					"raw": "{{URL}}/graphql",
					"host": [
						"{{URL}}"
					],
					"path": [
						"graphql"
					]
				}
			},
			"response": []
        },
        {
			"name": "GraphQL - iamUpdateAccount",
			"request": {
				"method": "POST",
				"header": [],
				"body": {
					"mode": "graphql",
					"graphql": {
						"query": "mutation ($payload:IamUpdateAccountInput!)\n{\n\tiamUpdateAccount (payload:$payload)\n\t{\n\t\tid\n\t\ttype\n\t\temail\n\t\tisActive\n\t\tclientId\n\t\tdApplicationCodes\n\t\tdPermissions\n\t\tdTenants\n\t\tdata\n\t\tcreatedAt\n\t\tupdatedAt\n\t}\n}",
						"variables": "{\n\t\"payload\":\n\t{\n\t\t\"id\": \"7587d893-0ac2-4ef2-83e1-c35b2f3fd213\", \n\t\t\"type\": \"SERVICE\", \n\t\t\"email\": \"jnjc2ixuqjeoyvgmhsqfs0h7eqkjpm3jy6palqivu5ynrdh1jslw5vpixmb6iu6blqm6ol5i5s1raq7xul9swb55zz9pawnh14pm6wqlgpsb5t8ahpm0882z\", \n\t\t\"isActive\": false, \n\t\t\"clientId\": \"0bec85f7-356c-4b0c-9343-84f6b60960f5\", \n\t\t\"dApplicationCodes\": { \"foo\" : \"bar\" }, \n\t\t\"dPermissions\": { \"foo\" : \"bar\" }, \n\t\t\"dTenants\": { \"foo\" : \"bar\" }, \n\t\t\"data\": { \"foo\" : \"bar\" }, \n\t\t\"roleIds\": [], \n\t\t\"tenantIds\": []\n\t}\n}"
					}
				},
				"url": {
					"raw": "{{URL}}/graphql",
					"host": [
						"{{URL}}"
					],
					"path": [
						"graphql"
					]
				}
			},
			"response": []
        },
        {
			"name": "GraphQL - iamDeleteAccountById",
			"request": {
				"method": "POST",
				"header": [],
				"body": {
					"mode": "graphql",
					"graphql": {
						"query": "mutation ($id:ID!)\n{\n\tiamDeleteAccountById (id:$id)\n\t{\n\t\tid\n\t\ttype\n\t\temail\n\t\tisActive\n\t\tclientId\n\t\tdApplicationCodes\n\t\tdPermissions\n\t\tdTenants\n\t\tdata\n\t\tcreatedAt\n\t\tupdatedAt\n\t}\n}",
						"variables": "{\n\t\"id\": \"7587d893-0ac2-4ef2-83e1-c35b2f3fd213\"\n}"
					}
				},
				"url": {
					"raw": "{{URL}}/graphql",
					"host": [
						"{{URL}}"
					],
					"path": [
						"graphql"
					]
				}
			},
			"response": []
        },
        {
			"name": "GraphQL - iamDeleteAccounts",
			"request": {
				"method": "POST",
				"header": [],
				"body": {
					"mode": "graphql",
					"graphql": {
						"query": "mutation ($query:QueryStatement)\n{\n\tiamDeleteAccounts (query: $query)\n\t{\n\t\tid\n\t\ttype\n\t\temail\n\t\tisActive\n\t\tclientId\n\t\tdApplicationCodes\n\t\tdPermissions\n\t\tdTenants\n\t\tdata\n\t\tcreatedAt\n\t\tupdatedAt\n\t}\n}",
						"variables": "{\n\t\"query\":\n\t{\n\t\t\"where\":\n\t\t{\n\t\t\t\"id\":\n\t\t\t{\n\t\t\t\t\"[substring]\": \"\"\n\t\t\t}\n\t\t}\n\t}\n}"
					}
				},
				"url": {
					"raw": "{{URL}}/graphql",
					"host": [
						"{{URL}}"
					],
					"path": [
						"graphql"
					]
				}
			},
			"response": []
        },
        {
			"name": "REST - iam/account",
			"request": {
				"method": "POST",
				"header": [
					{
						"key"   : "Content-Type",
						"name"  : "Content-Type",
						"type"  : "text",
						"value" : "application/json"
					}
				],
				"body": {
					"mode"  : "raw",
					"raw"   : "{\n\t\"id\": \"7587d893-0ac2-4ef2-83e1-c35b2f3fd213\", \n\t\"type\": \"SERVICE\", \n\t\"email\": \"nm62horgurjo3vo5y9bns5rz020o21knp20tq3tm037f1x5dg2txpatf4u5shv1bsj50ypl8rduimkimgodic8tuazylmptskrhgx91tnrdnmp3bl87n3t1c\", \n\t\"isActive\": false, \n\t\"clientId\": \"0bec85f7-356c-4b0c-9343-84f6b60960f5\", \n\t\"dApplicationCodes\": { \"foo\" : \"bar\" }, \n\t\"dPermissions\": { \"foo\" : \"bar\" }, \n\t\"dTenants\": { \"foo\" : \"bar\" }, \n\t\"data\": { \"foo\" : \"bar\" }, \n\t\"roleIds\": [], \n\t\"tenantIds\": []\n}",
					"options": {
						"raw": {
							"language": "json"
						}
					}
				},
				"url": {
					"raw": "{{URL}}/iam/account",
					"host": [
						"{{URL}}"
					],
					"path": [
						"iam",
						"account"
					]
				}
			},
			"response": []
        },
        {
			"name": "REST - iam/accounts",
			"request": {
				"method": "POST",
				"header": [
					{
						"key"   : "Content-Type",
						"name"  : "Content-Type",
						"type"  : "text",
						"value" : "application/json"
					}
				],
				"body": {
					"mode"  : "raw",
					"raw"   : "[\n\t{\n\t\t\"id\": \"3c255af2-beab-4940-96c6-7ccada321ff7\", \n\t\t\"type\": \"SERVICE\", \n\t\t\"email\": \"lk29txxww10yqs8et76utb1x0im51a6uaqfo98mun52nkrcvdo9eusrnmnj0vw7s7hg7drg8yv8kzts9hgqhit61pedp62a55o5y3ed7cwg24zxx3cuz1nr5\", \n\t\t\"isActive\": true, \n\t\t\"clientId\": \"a9ff4c9d-e294-4236-aac0-3d4c43e513be\", \n\t\t\"dApplicationCodes\": { \"foo\" : \"bar\" }, \n\t\t\"dPermissions\": { \"foo\" : \"bar\" }, \n\t\t\"dTenants\": { \"foo\" : \"bar\" }, \n\t\t\"data\": { \"foo\" : \"bar\" }, \n\t\t\"roleIds\": [], \n\t\t\"tenantIds\": []\n\t}, \n\t{\n\t\t\"id\": \"b38602ac-cc7d-4cf6-b797-bcde755ce0ba\", \n\t\t\"type\": \"USER\", \n\t\t\"email\": \"6srsy6b5n67m27biq021oa0hxk5jw24lzhxa247mo6m73vpilykawgb5iefr8yonpicqqwif9m990aszqc4p5q1icqr8xebk6fsqmdbnqb7znj21fk0xgtq4\", \n\t\t\"isActive\": true, \n\t\t\"clientId\": \"f3e11728-0c09-4cfa-8c20-62e510708bbf\", \n\t\t\"dApplicationCodes\": { \"foo\" : \"bar\" }, \n\t\t\"dPermissions\": { \"foo\" : \"bar\" }, \n\t\t\"dTenants\": { \"foo\" : \"bar\" }, \n\t\t\"data\": { \"foo\" : \"bar\" }, \n\t\t\"roleIds\": [], \n\t\t\"tenantIds\": []\n\t}, \n\t{\n\t\t\"id\": \"69e5026f-e0fb-4901-96bb-d6ea72201522\", \n\t\t\"type\": \"SERVICE\", \n\t\t\"email\": \"s1yvrcsb44huas6u96xpsrpzscbqvph98jeovksllmltzgsbk9lao2xhyewzy0ou10nmzvnjzb1q0lb5aaqpvqpxpz55n1w3q2adpd04ski7zp8j3sfknb3l\", \n\t\t\"isActive\": true, \n\t\t\"clientId\": \"db369912-8636-4592-80d9-d9151ecfb66e\", \n\t\t\"dApplicationCodes\": { \"foo\" : \"bar\" }, \n\t\t\"dPermissions\": { \"foo\" : \"bar\" }, \n\t\t\"dTenants\": { \"foo\" : \"bar\" }, \n\t\t\"data\": { \"foo\" : \"bar\" }, \n\t\t\"roleIds\": [], \n\t\t\"tenantIds\": []\n\t}, \n\t{\n\t\t\"id\": \"d53911c5-b802-4d3d-a762-b99f471e7f53\", \n\t\t\"type\": \"SERVICE\", \n\t\t\"email\": \"mnz6dixkju5892h9yh7439awo6e5825xv20e9ayq7bfjes4x6ugu1uu38eskcogzhbp9rvwebpt49hoi51qv3qjcvatck8qa0hih119ids499j2ei66jxosh\", \n\t\t\"isActive\": true, \n\t\t\"clientId\": \"62249161-4fc8-4fb1-bd02-a16988edb763\", \n\t\t\"dApplicationCodes\": { \"foo\" : \"bar\" }, \n\t\t\"dPermissions\": { \"foo\" : \"bar\" }, \n\t\t\"dTenants\": { \"foo\" : \"bar\" }, \n\t\t\"data\": { \"foo\" : \"bar\" }, \n\t\t\"roleIds\": [], \n\t\t\"tenantIds\": []\n\t}, \n\t{\n\t\t\"id\": \"08bf2236-b496-4523-b1ea-98a042381b59\", \n\t\t\"type\": \"USER\", \n\t\t\"email\": \"6s9rth48psuyhj633qt0lz4umc709qcl4tuuf08e74augqrr044uht5fn55gl8r2wotyhjm2qgy2iesmgu3l3hsuutlty4imgnpanpyt7rtjocu0dtcxzf2m\", \n\t\t\"isActive\": true, \n\t\t\"clientId\": \"74c70bac-89d3-4a7f-ae53-df407e1b3343\", \n\t\t\"dApplicationCodes\": { \"foo\" : \"bar\" }, \n\t\t\"dPermissions\": { \"foo\" : \"bar\" }, \n\t\t\"dTenants\": { \"foo\" : \"bar\" }, \n\t\t\"data\": { \"foo\" : \"bar\" }, \n\t\t\"roleIds\": [], \n\t\t\"tenantIds\": []\n\t}, \n\t{\n\t\t\"id\": \"f78d319a-715e-43a8-9213-072141aa4f97\", \n\t\t\"type\": \"SERVICE\", \n\t\t\"email\": \"skic1byagam7o1zgt00e1f06b4ugsqzvsmeolnu9bjwjtoizspirmmj3zgjop1emnknognl1y6cccfvul1w5rspf0yk53ylku9vibptf6ldcyrboix0awvvw\", \n\t\t\"isActive\": false, \n\t\t\"clientId\": \"4e1c7a26-f6cc-48d5-b780-e3c0d35a0c39\", \n\t\t\"dApplicationCodes\": { \"foo\" : \"bar\" }, \n\t\t\"dPermissions\": { \"foo\" : \"bar\" }, \n\t\t\"dTenants\": { \"foo\" : \"bar\" }, \n\t\t\"data\": { \"foo\" : \"bar\" }, \n\t\t\"roleIds\": [], \n\t\t\"tenantIds\": []\n\t}, \n\t{\n\t\t\"id\": \"851cf0cb-6370-423f-a37c-dd0d0d9a6350\", \n\t\t\"type\": \"USER\", \n\t\t\"email\": \"1vs8d6g6n4pdugv79qu8q8m7rvx3qsf7ixuwnhtyc66cmxba21nmumeyw8kg1mnhypr3vdcokd25jtwn63574ghb1trekaxprzn1x8jdspytb1x7s9hy33r4\", \n\t\t\"isActive\": false, \n\t\t\"clientId\": \"08418509-6ccf-410f-8a88-62cb87f9dac1\", \n\t\t\"dApplicationCodes\": { \"foo\" : \"bar\" }, \n\t\t\"dPermissions\": { \"foo\" : \"bar\" }, \n\t\t\"dTenants\": { \"foo\" : \"bar\" }, \n\t\t\"data\": { \"foo\" : \"bar\" }, \n\t\t\"roleIds\": [], \n\t\t\"tenantIds\": []\n\t}, \n\t{\n\t\t\"id\": \"e433fd37-e67d-4619-91e3-f25a167b7b28\", \n\t\t\"type\": \"SERVICE\", \n\t\t\"email\": \"r6fyz4g13l9pqo53sw0eyehcr8yfp10flc99vwblewa6prkmiwnqqcrakw9ye4tyf2vuatmyvvkwfpbh761oltnmt3pe09ju4wlkbcni1zx8ovz8qj4w1fok\", \n\t\t\"isActive\": true, \n\t\t\"clientId\": \"f829a55d-dad1-4ef9-add1-70a9aaaf833e\", \n\t\t\"dApplicationCodes\": { \"foo\" : \"bar\" }, \n\t\t\"dPermissions\": { \"foo\" : \"bar\" }, \n\t\t\"dTenants\": { \"foo\" : \"bar\" }, \n\t\t\"data\": { \"foo\" : \"bar\" }, \n\t\t\"roleIds\": [], \n\t\t\"tenantIds\": []\n\t}, \n\t{\n\t\t\"id\": \"62c9af8f-03bb-4abe-83c4-c6889c9b119a\", \n\t\t\"type\": \"SERVICE\", \n\t\t\"email\": \"1kblc1vpxcbc62ouoc0qcxny5yoted06jbcc7fsu4rk7ocyldttfae4ywdjkwzj6hpl1o34c35wqy9ylt7chjhb4cjkok39khpyctje1xk1mkm8x4o0dh0o1\", \n\t\t\"isActive\": true, \n\t\t\"clientId\": \"374f8691-ff8a-4b6f-9fa0-7bd3568f6194\", \n\t\t\"dApplicationCodes\": { \"foo\" : \"bar\" }, \n\t\t\"dPermissions\": { \"foo\" : \"bar\" }, \n\t\t\"dTenants\": { \"foo\" : \"bar\" }, \n\t\t\"data\": { \"foo\" : \"bar\" }, \n\t\t\"roleIds\": [], \n\t\t\"tenantIds\": []\n\t}, \n\t{\n\t\t\"id\": \"01777abf-1b20-4bab-8833-c8ba79f85317\", \n\t\t\"type\": \"USER\", \n\t\t\"email\": \"1v0nkg95zsxkd9utknv1sbdqq9av4mckne4n7fch2chfyisqjlh6lt0c14hqctd8qgxdzxspx33l1vdsn8mv1szgut2jtb3cd4qaqml08ltsiyxoko8l9te0\", \n\t\t\"isActive\": false, \n\t\t\"clientId\": \"2203588c-5e21-4dba-89f9-add56c7ab6ac\", \n\t\t\"dApplicationCodes\": { \"foo\" : \"bar\" }, \n\t\t\"dPermissions\": { \"foo\" : \"bar\" }, \n\t\t\"dTenants\": { \"foo\" : \"bar\" }, \n\t\t\"data\": { \"foo\" : \"bar\" }, \n\t\t\"roleIds\": [], \n\t\t\"tenantIds\": []\n\t}, \n\t{\n\t\t\"id\": \"00bf1479-5c2b-40dd-8e62-cfe9d830e336\", \n\t\t\"type\": \"USER\", \n\t\t\"email\": \"kvugppg0mbgxkyja3vi1vubkx7l0bxp6qsfjbhyxg4su761a4zm4t3c3y9vnhsraxz13wa74ceu50mheywjm65u3qf60l79qxv6fnn68ug51i74cyavd0myb\", \n\t\t\"isActive\": false, \n\t\t\"clientId\": \"3b64bdad-fe08-461f-a8a3-86836bcc08a1\", \n\t\t\"dApplicationCodes\": { \"foo\" : \"bar\" }, \n\t\t\"dPermissions\": { \"foo\" : \"bar\" }, \n\t\t\"dTenants\": { \"foo\" : \"bar\" }, \n\t\t\"data\": { \"foo\" : \"bar\" }, \n\t\t\"roleIds\": [], \n\t\t\"tenantIds\": []\n\t}, \n\t{\n\t\t\"id\": \"b9ef8747-bf94-415b-8c37-07b639dfa0ca\", \n\t\t\"type\": \"SERVICE\", \n\t\t\"email\": \"k5dom9jt7kl3wj9a432fz5b95y18wf80or5j1j14vs1uxddior14htldqclqz3o1r6j5bdhcab9yk3c8gqo9bugd0t23vq1g12ufxji573vsfo3l3hjqk1nz\", \n\t\t\"isActive\": false, \n\t\t\"clientId\": \"8c78508c-e700-45dc-b979-7e09cbc19280\", \n\t\t\"dApplicationCodes\": { \"foo\" : \"bar\" }, \n\t\t\"dPermissions\": { \"foo\" : \"bar\" }, \n\t\t\"dTenants\": { \"foo\" : \"bar\" }, \n\t\t\"data\": { \"foo\" : \"bar\" }, \n\t\t\"roleIds\": [], \n\t\t\"tenantIds\": []\n\t}, \n\t{\n\t\t\"id\": \"2d787850-7ade-4d5f-9ef1-6e7e6aa08d0e\", \n\t\t\"type\": \"SERVICE\", \n\t\t\"email\": \"41iig1nsjacwivvmiiqikpq963b3vi43vfawesiof4jpm2t8x7hx1w9qgkzvke95styqwf9ct1v63mxbpl2jpvmlmcbyvaptzzyqmngdwnsm86mz6l484enh\", \n\t\t\"isActive\": false, \n\t\t\"clientId\": \"d55f7fee-08b3-46ac-a360-e2db4332f6c2\", \n\t\t\"dApplicationCodes\": { \"foo\" : \"bar\" }, \n\t\t\"dPermissions\": { \"foo\" : \"bar\" }, \n\t\t\"dTenants\": { \"foo\" : \"bar\" }, \n\t\t\"data\": { \"foo\" : \"bar\" }, \n\t\t\"roleIds\": [], \n\t\t\"tenantIds\": []\n\t}, \n\t{\n\t\t\"id\": \"4e728c6d-484d-484f-b7e6-6f82125d0a6e\", \n\t\t\"type\": \"USER\", \n\t\t\"email\": \"3k4l0ncolgulpmgia0nwsjiis5rmfot24fefl4zlpbpue27yepuqucuxrfjxsctwz87t8iswlgl87inurgb67dp96ipy9bbpcwh834a613hfno4r9pqqtxko\", \n\t\t\"isActive\": false, \n\t\t\"clientId\": \"3e5e66ff-d230-41c3-880c-33fa703e5b2f\", \n\t\t\"dApplicationCodes\": { \"foo\" : \"bar\" }, \n\t\t\"dPermissions\": { \"foo\" : \"bar\" }, \n\t\t\"dTenants\": { \"foo\" : \"bar\" }, \n\t\t\"data\": { \"foo\" : \"bar\" }, \n\t\t\"roleIds\": [], \n\t\t\"tenantIds\": []\n\t}, \n\t{\n\t\t\"id\": \"0345a633-5dd2-4923-9177-8f69b139af69\", \n\t\t\"type\": \"SERVICE\", \n\t\t\"email\": \"0xw5ozydhttbrd5duh13rr28qnpy9cmm0ck9v34bfbyt91xv084hujp2k1uk8tvk6162dzt03soo72rb5r77mey88792zda8jnavuflco5kib9j00s35hd96\", \n\t\t\"isActive\": true, \n\t\t\"clientId\": \"c344243c-1ab9-41d8-a79b-6164d4831932\", \n\t\t\"dApplicationCodes\": { \"foo\" : \"bar\" }, \n\t\t\"dPermissions\": { \"foo\" : \"bar\" }, \n\t\t\"dTenants\": { \"foo\" : \"bar\" }, \n\t\t\"data\": { \"foo\" : \"bar\" }, \n\t\t\"roleIds\": [], \n\t\t\"tenantIds\": []\n\t}, \n\t{\n\t\t\"id\": \"22945f54-ef73-46d0-b8fd-6ede34c2e08e\", \n\t\t\"type\": \"SERVICE\", \n\t\t\"email\": \"3sf2998rf5ll7ldjfqvt8xfpg9fr8s5eolquggdxxo83qha5q6rhme4lr1m2r4d5la1bp6kqb3cng78mrsxjq0ug5v5nhu0swvfgd5a283vofaz9dx1fu1l3\", \n\t\t\"isActive\": true, \n\t\t\"clientId\": \"d8b6228e-8d24-4fda-8695-f35ef5093963\", \n\t\t\"dApplicationCodes\": { \"foo\" : \"bar\" }, \n\t\t\"dPermissions\": { \"foo\" : \"bar\" }, \n\t\t\"dTenants\": { \"foo\" : \"bar\" }, \n\t\t\"data\": { \"foo\" : \"bar\" }, \n\t\t\"roleIds\": [], \n\t\t\"tenantIds\": []\n\t}, \n\t{\n\t\t\"id\": \"2b468908-32f3-4583-9d42-ac5d2a48a80e\", \n\t\t\"type\": \"SERVICE\", \n\t\t\"email\": \"9ddfjh7vxqvs3auu9xd3gg6quqf74en32sbip4rtjelc3ftd9whvuecz05frwdid5kec6qd24e4s5dbr99951qhl0tf6fvablc21pwpcehbyb8yyb1t43b5z\", \n\t\t\"isActive\": false, \n\t\t\"clientId\": \"265d40f1-b1d0-428f-97e8-3b56c7802972\", \n\t\t\"dApplicationCodes\": { \"foo\" : \"bar\" }, \n\t\t\"dPermissions\": { \"foo\" : \"bar\" }, \n\t\t\"dTenants\": { \"foo\" : \"bar\" }, \n\t\t\"data\": { \"foo\" : \"bar\" }, \n\t\t\"roleIds\": [], \n\t\t\"tenantIds\": []\n\t}, \n\t{\n\t\t\"id\": \"fe495215-427b-4d83-adc5-da3e8c9cb2be\", \n\t\t\"type\": \"SERVICE\", \n\t\t\"email\": \"u1h0fix1mn8ks4o2musi5ryng0ctk5b0tfeu5fbke7b4jntbhx7gid7u3gn4ohjbq6lnlg5qwwpghue9tqjwhr7jm801t6x2iwk3polpkl8wtc6rqvdffkf2\", \n\t\t\"isActive\": false, \n\t\t\"clientId\": \"55774c79-7b7a-4da9-98f2-02edf1e6e13e\", \n\t\t\"dApplicationCodes\": { \"foo\" : \"bar\" }, \n\t\t\"dPermissions\": { \"foo\" : \"bar\" }, \n\t\t\"dTenants\": { \"foo\" : \"bar\" }, \n\t\t\"data\": { \"foo\" : \"bar\" }, \n\t\t\"roleIds\": [], \n\t\t\"tenantIds\": []\n\t}, \n\t{\n\t\t\"id\": \"0c046a20-4b20-44cd-9e54-b1e78ebb45db\", \n\t\t\"type\": \"USER\", \n\t\t\"email\": \"dhqg5q2txrchoct7bx0zdm3dul1xd9dvp5ff1l6avloh7wmgb2t302ozv5p2b983wxbptznyrxvccdlqij3jg7o9b6dlbjn4u2jk1kg5pzrrhrvwsc0ut899\", \n\t\t\"isActive\": true, \n\t\t\"clientId\": \"b8cfaa51-dd43-4056-acf8-4f85cd138569\", \n\t\t\"dApplicationCodes\": { \"foo\" : \"bar\" }, \n\t\t\"dPermissions\": { \"foo\" : \"bar\" }, \n\t\t\"dTenants\": { \"foo\" : \"bar\" }, \n\t\t\"data\": { \"foo\" : \"bar\" }, \n\t\t\"roleIds\": [], \n\t\t\"tenantIds\": []\n\t}, \n\t{\n\t\t\"id\": \"d21b871c-6f7f-4477-bb3a-aea4af7cea9c\", \n\t\t\"type\": \"USER\", \n\t\t\"email\": \"z6jh3xjcky877qwpvkrn124gwyg0pjpkied4zmdyzv7ix3osxhp4bsepqw6svu45x5033dhoog2g4d2q7jtcg2kixbujfjxavg7sadxs2vx4vy1jkjj1h82o\", \n\t\t\"isActive\": false, \n\t\t\"clientId\": \"a8c85cad-de1b-4043-b86c-3096a03f6d33\", \n\t\t\"dApplicationCodes\": { \"foo\" : \"bar\" }, \n\t\t\"dPermissions\": { \"foo\" : \"bar\" }, \n\t\t\"dTenants\": { \"foo\" : \"bar\" }, \n\t\t\"data\": { \"foo\" : \"bar\" }, \n\t\t\"roleIds\": [], \n\t\t\"tenantIds\": []\n\t}\n]",
					"options": {
						"raw": {
							"language": "json"
						}
					}
				},
				"url": {
					"raw": "{{URL}}/iam/accounts",
					"host": [
						"{{URL}}"
					],
					"path": [
						"iam",
						"accounts"
					]
				}
			},
			"response": []
        },
        {
			"name": "REST - iam/accounts/paginate",
			"protocolProfileBehavior": {
				"disableBodyPruning": true
			},
			"request": {
				"method": "GET",
				"header": [
					{
						"key": "Content-Type",
						"name": "Content-Type",
						"type": "text",
						"value": "application/json"
					}
				],
				"body": {
					"mode": "raw",
					"raw": "{\n\t\"query\":\n\t{\n\t\t\"offset\": 0,\n\t\t\"limit\": 10\n\t}\n}",
					"options": {
						"raw": {
							"language": "json"
						}
					}
				},
				"url": {
					"raw": "{{URL}}/iam/accounts/paginate",
					"host": [
						"{{URL}}"
					],
					"path": [
						"iam",
                        "accounts",
                        "paginate"
					]
				}
			},
			"response": []
        },
        {
			"name": "REST - iam/accounts",
			"protocolProfileBehavior": {
				"disableBodyPruning": true
			},
			"request": {
				"method": "GET",
				"header": [
					{
						"key": "Content-Type",
						"name": "Content-Type",
						"type": "text",
						"value": "application/json"
					}
				],
				"body": {
					"mode": "raw",
					"raw": "{\n\t\"query\":\n\t{\n\t\t\"where\":\n\t\t{ \n\t\t\t\"id\": \"7587d893-0ac2-4ef2-83e1-c35b2f3fd213\"\n\t\t}\n\t}\n}",
					"options": {
						"raw": {
							"language": "json"
						}
					}
				},
				"url": {
					"raw": "{{URL}}/iam/accounts",
					"host": [
						"{{URL}}"
					],
					"path": [
						"iam",
						"accounts"
					]
				}
			},
			"response": []
        },
        {
			"name": "REST - iam/account",
			"protocolProfileBehavior": {
				"disableBodyPruning": true
			},
			"request": {
				"method": "GET",
				"header": [
					{
						"key": "Content-Type",
						"name": "Content-Type",
						"type": "text",
						"value": "application/json"
					}
				],
				"body": {
					"mode": "raw",
					"raw": "{\n\t\"query\":\n\t{\n\t\t\"where\":\n\t\t{\n\t\t\t\"id\": \"7587d893-0ac2-4ef2-83e1-c35b2f3fd213\"\n\t\t}\n\t}\n}",
					"options": {
						"raw": {
							"language": "json"
						}
					}
				},
				"url": {
					"raw": "{{URL}}/iam/account",
					"host": [
						"{{URL}}"
					],
					"path": [
						"iam",
						"account"
					]
				}
			},
			"response": []
        },
        {
			"name": "REST - iam/account/{id}",
			"protocolProfileBehavior": {
				"disableBodyPruning": true
			},
			"request": {
				"method": "GET",
				"header": [
					{
						"key": "Content-Type",
						"name": "Content-Type",
						"type": "text",
						"value": "application/json"
					}
				],
				"body": {
					"mode": "raw",
					"raw": "",
					"options": {
						"raw": {
							"language": "json"
						}
					}
				},
				"url": {
					"raw": "{{URL}}/iam/account/7587d893-0ac2-4ef2-83e1-c35b2f3fd213",
					"host": [
						"{{URL}}"
					],
					"path": [
						"iam",
						"account",
						"7587d893-0ac2-4ef2-83e1-c35b2f3fd213"
					]
				}
			},
			"response": []
        },
        {
			"name": "REST - iam/account",
			"request": {
				"method": "PUT",
				"header": [
					{
						"key": "Content-Type",
						"name": "Content-Type",
						"type": "text",
						"value": "application/json"
					}
				],
				"body": {
					"mode": "raw",
					"raw"   : "{\n\t\"id\": \"7587d893-0ac2-4ef2-83e1-c35b2f3fd213\", \n\t\"type\": \"SERVICE\", \n\t\"email\": \"awscpvyv0peqc1lq2v204j1j6zsijyh47tfeejy3ihlvn23g1ywikkexc66dwdxa9imoxb5tj1euakkp28yxh7gjgxpzvmodlusi81s7a41eg33l6ng9ecuj\", \n\t\"isActive\": true, \n\t\"clientId\": \"0bec85f7-356c-4b0c-9343-84f6b60960f5\", \n\t\"dApplicationCodes\": { \"foo\" : \"bar\" }, \n\t\"dPermissions\": { \"foo\" : \"bar\" }, \n\t\"dTenants\": { \"foo\" : \"bar\" }, \n\t\"data\": { \"foo\" : \"bar\" }, \n\t\"roleIds\": [], \n\t\"tenantIds\": []\n}",
					"options": {
						"raw": {
							"language": "json"
						}
					}
				},
				"url": {
					"raw": "{{URL}}/iam/account",
					"host": [
						"{{URL}}"
					],
					"path": [
						"iam",
						"account"
					]
				}
			},
			"response": []
        },
        {
			"name": "REST - iam/account/{id}",
			"request": {
				"method": "DELETE",
				"header": [
					{
						"key": "Content-Type",
						"name": "Content-Type",
						"type": "text",
						"value": "application/json"
					}
				],
				"body": {
					"mode": "raw",
					"raw": "",
					"options": {
						"raw": {
							"language": "json"
						}
					}
				},
				"url": {
					"raw": "{{URL}}/iam/account/7587d893-0ac2-4ef2-83e1-c35b2f3fd213",
					"host": [
						"{{URL}}"
					],
					"path": [
						"iam",
						"account",
						"7587d893-0ac2-4ef2-83e1-c35b2f3fd213"
					]
				}
			},
			"response": []
		},
        {
			"name": "REST - iam/accounts",
			"request": {
				"method": "DELETE",
				"header": [
					{
						"key": "Content-Type",
						"name": "Content-Type",
						"type": "text",
						"value": "application/json"
					}
				],
				"body": {
					"mode": "raw",
					"raw": "{\n\t\"query\":\n\t{\n\t\t\"where\":\n\t\t{\n\t\t\t\"id\":\n\t\t\t{\n\t\t\t\t\"[substring]\": \"\"\n\t\t\t}\n\t\t}\n\t}\n}",
					"options": {
						"raw": {
							"language": "json"
						}
					}
				},
				"url": {
					"raw": "{{URL}}/iam/accounts",
					"host": [
						"{{URL}}"
					],
					"path": [
						"iam",
						"accounts"
					]
				}
			},
			"response": []
		}
    ],
    "variable": [
		{
			"id": "197e3acf-a23d-47ae-ad21-b014eda84fc6",
			"key": "URL",
			"value": "http://localhost:8080",
			"type": "string"
		}
	]
}